{
  "id": "press-2025-04-03-043_농림축산식품부_산불_피해_농업인의_조속한_영농_재개를_위해_민_관이_합심하여_농기계_총력_지원-fcb0d43b61",
  "detailPath": "docs/details/press/press-2025-04-03-043_농림축산식품부_산불_피해_농업인의_조속한_영농_재개를_위해_민_관이_합심하여_농기계_총력_지원-fcb0d43b61.json",
  "layer": "press",
  "file": "043_농림축산식품부_산불_피해_농업인의_조속한_영농_재개를_위해_민_관이_합심하여_농기계_총력_지원.md",
  "title": "산불 피해 농업인의 조속한 영농 재개를 위해 민-관이 합심하여 농기계 총력 지원",
  "institution": "농림축산식품부",
  "ministry": "농림축산식품부",
  "date": "2025-04-03",
  "approveDate": "04/03/2025 10:30:00",
  "docType": "brief",
  "groupingCode": "brief",
  "newsItemId": "156682389",
  "originalUrl": "https://www.korea.kr/briefing/pressReleaseView.do?newsId=156682389&call_from=openData",
  "source": "policy-briefing-api",
  "excerpt": "농림축산식품부(장관 송미령, 이하 농식품부)는 울산∙경북∙경남지역 산불 피해를 입은 농업인의 조속한 영농 재개를 위해 지자체, 농기계업체 등과 협력하여 농기계 긴급 지원 대책을 추진한다. 첫째, 피해 농업인이 바로 영농활동을 할 수 있도록 임대사업소에서 농기계를 무상으로 빌려서 사용할 수 있도록 조치하였다. 이를 위해 4월 2일부터 봄철 영농기에 많이 쓰는 트랙터, 이앙기, 관리기, 경운기,",
  "path": "data/2025/2025-04/2025-04-03/043_농림축산식품부_산불_피해_농업인의_조속한_영농_재개를_위해_민_관이_합심하여_농기계_총력_지원.md"
}