{
  "id": "press-2025-06-09-025_조달청_조달청_물품구매_적격심사_신인도_정비로_두_마리_토끼_잡는다",
  "detailPath": "docs/details/press/press-2025-06-09-025_조달청_조달청_물품구매_적격심사_신인도_정비로_두_마리_토끼_잡는다.json",
  "layer": "press",
  "file": "025_조달청_조달청_물품구매_적격심사_신인도_정비로_두_마리_토끼_잡는다.md",
  "title": "조달청, 물품구매 적격심사 신인도 정비로 두 마리 토끼 잡는다",
  "institution": "조달청",
  "ministry": "조달청",
  "date": "2025-06-09",
  "approveDate": "06/09/2025 09:23:51",
  "docType": "brief",
  "groupingCode": "brief",
  "newsItemId": "156718093",
  "originalUrl": "https://www.korea.kr/briefing/pressReleaseView.do?newsId=156718093&call_from=openData",
  "source": "policy-briefing-api",
  "excerpt": "조달청, 물품구매 적격심사 신인도 정비로 두 마리 토끼 잡는다 - 저출생 대응, 탄소중립, 고용 창출 등 주요 정부 정책 지원 강화 - 기술·품질 평점 상향으로 기업의 경쟁력 강화에 기여 조달청(청장 임기근)은 적격심사에 활용되는 신인도*의 정비를 통해 정부정책 지원의 효과성은 높이고 기업의 경쟁력은 강화하는 방향으로 「조달청 물품구매 적격심사 세부기준」 및 「조달청 중소기업자간 경쟁물품 계",
  "path": "data/2025/2025-06/2025-06-09/025_조달청_조달청_물품구매_적격심사_신인도_정비로_두_마리_토끼_잡는다.md"
}