{
  "id": "press-2025-01-20-062_행정안전부_행안부_해수부_영해기점을_알리기_위해_2025년_올해의_섬으로_완도군_여서도_지정",
  "detailPath": "docs/details/press/press-2025-01-20-062_행정안전부_행안부_해수부_영해기점을_알리기_위해_2025년_올해의_섬으로_완도군_여서도_지정.json",
  "layer": "press",
  "file": "062_행정안전부_행안부_해수부_영해기점을_알리기_위해_2025년_올해의_섬으로_완도군_여서도_지정.md",
  "title": "행안부&middot;해수부, 영해기점을 알리기 위해 2025년 올해의 섬으로 완도군 ‘여서도’ 지정",
  "institution": "행정안전부",
  "ministry": "행정안전부",
  "date": "2025-01-20",
  "approveDate": "01/20/2025 12:00:00",
  "docType": "brief",
  "groupingCode": "brief",
  "newsItemId": "156671007",
  "originalUrl": "https://www.korea.kr/briefing/pressReleaseView.do?newsId=156671007&call_from=openData",
  "source": "policy-briefing-api",
  "excerpt": "행안부·해수부, 영해기점을 알리기 위해 2025년 올해의 섬으로 완도군 ‘여서도’ 지정 -> 7개 영해기점 유인섬의 중요성 알리기 위해 부처 공동으로 올해의 섬 지정 행정안전부(이하 행안부)와 해양수산부(이하 해수부)는 ‘2025년 올해의 섬’ 으로 전라남도 완도군에 위치한 영해기점 유인섬인 ‘여서도(麗瑞島)’를 지정했다고 밝혔다. 자세한 내용은 첨부를 참고하시기 바랍니다.",
  "path": "data/2025/2025-01/2025-01-20/062_행정안전부_행안부_해수부_영해기점을_알리기_위해_2025년_올해의_섬으로_완도군_여서도_지정.md"
}