{
  "id": "press-2026-01-14-055_소방청_화재_현장에_정답은_없다_최적의_해법_찾는다_전국_실화재_교관단_머리_맞대-080d4ea7a1",
  "detailPath": "docs/details/press/press-2026-01-14-055_소방청_화재_현장에_정답은_없다_최적의_해법_찾는다_전국_실화재_교관단_머리_맞대-080d4ea7a1.json",
  "layer": "press",
  "file": "055_소방청_화재_현장에_정답은_없다_최적의_해법_찾는다_전국_실화재_교관단_머리_맞대.md",
  "title": "&quot;화재 현장에 정답은 없다, 최적의 해법 찾는다&quot;… 전국 실화재 교관단 머리 맞대",
  "institution": "소방청",
  "ministry": "소방청",
  "date": "2026-01-14",
  "approveDate": "01/14/2026 14:00:00",
  "docType": "brief",
  "groupingCode": "brief",
  "newsItemId": "156739658",
  "originalUrl": "https://www.korea.kr/briefing/pressReleaseView.do?newsId=156739658&call_from=openData",
  "source": "policy-briefing-api",
  "excerpt": "\"화재 현장에 정답은 없다, 최적의 해법 찾는다\"… 전국 실화재 교관단 머리 맞대 - 중앙소방학교, 15~16일 '2026년 전국 소방학교 실화재 교수 학술연구' 개최 - 국외 선진 전술 공유 및 한국형 실화재 훈련 표준화 방안 모색 - '전술지휘훈련장' 등 첨단 시설 활용해 과학적 화재 대응 기틀 마련",
  "path": "data/2026/2026-01/2026-01-14/055_소방청_화재_현장에_정답은_없다_최적의_해법_찾는다_전국_실화재_교관단_머리_맞대.md"
}