{
  "id": "press-2025-12-24-097_국무조정실_보도자료_제4차_부동산_불법행위_대응협의회_보도자료-6967fb6467",
  "detailPath": "docs/details/press/press-2025-12-24-097_국무조정실_보도자료_제4차_부동산_불법행위_대응협의회_보도자료-6967fb6467.json",
  "layer": "press",
  "file": "097_국무조정실_보도자료_제4차_부동산_불법행위_대응협의회_보도자료.md",
  "title": "[보도자료] 제4차 부동산 불법행위 대응협의회 보도자료",
  "institution": "국무조정실",
  "ministry": "국무조정실",
  "date": "2025-12-24",
  "approveDate": "12/24/2025 16:30:00",
  "docType": "brief",
  "groupingCode": "brief",
  "newsItemId": "156736786",
  "originalUrl": "https://www.korea.kr/briefing/pressReleaseView.do?newsId=156736786&call_from=openData",
  "source": "policy-briefing-api",
  "excerpt": "제4차 부동산 불법행위 대응협의회, 국토부·금융위·경찰청 집중 조사·수사 결과 발표 - 국토부, '25년 하반기 이상거래 기획조사 결과 위법 의심거래 1,002건 적발 - 금융위, 사업자대출 관련 금융회사 자체점검 134건, 현장점검 32건 등 적발",
  "path": "data/2025/2025-12/2025-12-24/097_국무조정실_보도자료_제4차_부동산_불법행위_대응협의회_보도자료.md"
}