{
  "id": "press-2025-02-24-042_특허청_첨단산업분야_수출기업의_해외_지식재산_거래_돕는다",
  "detailPath": "docs/details/press/press-2025-02-24-042_특허청_첨단산업분야_수출기업의_해외_지식재산_거래_돕는다.json",
  "layer": "press",
  "file": "042_특허청_첨단산업분야_수출기업의_해외_지식재산_거래_돕는다.md",
  "title": "첨단산업분야 수출기업의 해외 지식재산 거래 돕는다!",
  "institution": "특허청",
  "ministry": "특허청",
  "date": "2025-02-24",
  "approveDate": "02/24/2025 10:28:48",
  "docType": "brief",
  "groupingCode": "brief",
  "newsItemId": "156675646",
  "originalUrl": "https://www.korea.kr/briefing/pressReleaseView.do?newsId=156675646&call_from=openData",
  "source": "policy-briefing-api",
  "excerpt": "첨단산업분야 수출기업의 해외 지식재산 거래 돕는다! - 특허청, 2025년도 「해외 지식재산 거래 지원사업」 신규 모집(2.24~3.19) - - 해외 지식재산 거래 중개를 희망하는 중소·중견기업 모집 - ㅇ 반도체 EUV(극자외선) 장비 전문기업 A사는 지식재산전문관을 통해 네덜란드 기업 B사가 보유한 EUV광원 기술 도입을 위한 전용실시권 계약을 체결하였으며, 도입한 기술을 활용한 후속 ",
  "path": "data/2025/2025-02/2025-02-24/042_특허청_첨단산업분야_수출기업의_해외_지식재산_거래_돕는다.md"
}