{
  "id": "press-2025-12-01-099_경찰청_운전학원의_도로_연수_교육_집_앞에서도_가능",
  "detailPath": "docs/details/press/press-2025-12-01-099_경찰청_운전학원의_도로_연수_교육_집_앞에서도_가능.json",
  "layer": "press",
  "file": "099_경찰청_운전학원의_도로_연수_교육_집_앞에서도_가능.md",
  "title": "운전학원의 도로 연수 교육 집 앞에서도 가능",
  "institution": "경찰청",
  "ministry": "경찰청",
  "date": "2025-12-01",
  "approveDate": "12/01/2025 15:12:39",
  "docType": "brief",
  "groupingCode": "brief",
  "newsItemId": "156732427",
  "originalUrl": "https://www.korea.kr/briefing/pressReleaseView.do?newsId=156732427&call_from=openData",
  "source": "policy-briefing-api",
  "excerpt": "운전학원의 도로 연수 교육 집 앞에서도 가능 관련 보도자료 내용입니다.",
  "path": "data/2025/2025-12/2025-12-01/099_경찰청_운전학원의_도로_연수_교육_집_앞에서도_가능.md"
}