{
  "id": "press-2026-02-04-100_재정경제부_바이오헬스_수출_지원_위해_오송서_원스톱_수출_119_개최-b121b35415",
  "detailPath": "docs/details/press/press-2026-02-04-100_재정경제부_바이오헬스_수출_지원_위해_오송서_원스톱_수출_119_개최-b121b35415.json",
  "layer": "press",
  "file": "100_재정경제부_바이오헬스_수출_지원_위해_오송서_원스톱_수출_119_개최.md",
  "title": "바이오헬스 수출 지원 위해 오송서 원스톱 수출 119 개최",
  "institution": "재정경제부",
  "ministry": "재정경제부",
  "date": "2026-02-05",
  "approveDate": "02/05/2026 00:00:00",
  "docType": "brief",
  "groupingCode": "brief",
  "newsItemId": "156743257",
  "originalUrl": "https://www.korea.kr/briefing/pressReleaseView.do?newsId=156743257&call_from=openData",
  "source": "policy-briefing-api",
  "excerpt": "재정경제부 원스톱 수출·수주지원단(단장: 이형일 재정경제부 1차관)은 2.5일(목) 오송 생명과학단지에서 의약품, 의료기기, 화장품 등 바이오헬스 업계와 함께 '원스톱 수출 119' 간담회를 개최하였습니다. ※ 자세한 내용은 첨부자료를 확인하여 주시기 바랍니다. 문의. 재정경제부 원스톱수출수주지원단 수출총괄팀 이한슬 (02-6000-5776)",
  "path": "data/2026/2026-02/2026-02-04/100_재정경제부_바이오헬스_수출_지원_위해_오송서_원스톱_수출_119_개최.md"
}