{
  "id": "press-2026-03-25-133_농촌진흥청_고구마_안정_생산_아주심기_전후_철저한_관리가_핵심",
  "detailPath": "docs/details/press/press-2026-03-25-133_농촌진흥청_고구마_안정_생산_아주심기_전후_철저한_관리가_핵심.json",
  "layer": "press",
  "file": "133_농촌진흥청_고구마_안정_생산_아주심기_전후_철저한_관리가_핵심.md",
  "title": "고구마 안정 생산, '아주심기' 전후 철저한 관리가 핵심",
  "institution": "농촌진흥청",
  "ministry": "농촌진흥청",
  "date": "2026-03-25",
  "approveDate": "03/25/2026 18:42:57",
  "docType": "brief",
  "groupingCode": "brief",
  "newsItemId": "156750919",
  "originalUrl": "https://www.korea.kr/briefing/pressReleaseView.do?newsId=156750919&call_from=openData",
  "source": "policy-briefing-api",
  "excerpt": "농촌진흥청(청장 이승돈)은 본격적인 고구마 아주심기 시기를 맞아 최근 빈번해진 이상기상 피해를 예방하고, 안정적 수확을 위한 단계별 관리 요령을 소개했다. 최근 잦은 저온 현상과 집중 호우, 고온 건조 등 기상 변화로 피해가 증가함에 따라 아주심기 전후 세심한 관리가 어느 때보다 중요해지고 있다. (모 준비) 병에 걸리지 않고 마디가 굵은 튼튼한 모를 골라야 한다. 기온이나 토양 수분이 알맞",
  "path": "data/2026/2026-03/2026-03-25/133_농촌진흥청_고구마_안정_생산_아주심기_전후_철저한_관리가_핵심.md"
}