{
  "id": "press-2025-03-19-060_보건복지부_개방형_실험실_운영_사업_주관기관_신규_선정-1eeb89ae49",
  "detailPath": "docs/details/press/press-2025-03-19-060_보건복지부_개방형_실험실_운영_사업_주관기관_신규_선정-1eeb89ae49.json",
  "layer": "press",
  "file": "060_보건복지부_개방형_실험실_운영_사업_주관기관_신규_선정.md",
  "title": "개방형 실험실 운영 사업 주관기관 신규 선정",
  "institution": "보건복지부",
  "ministry": "보건복지부",
  "date": "2025-03-19",
  "approveDate": "03/19/2025 11:01:09",
  "docType": "brief",
  "groupingCode": "brief",
  "newsItemId": "156679613",
  "originalUrl": "https://www.korea.kr/briefing/pressReleaseView.do?newsId=156679613&call_from=openData",
  "source": "policy-briefing-api",
  "excerpt": "「개방형 실험실 운영」사업 주관기관 신규 선정 - 2년간(2025~2026) 병원 내 창업기업 공간 지원 및 임상 자문 등 실시 - 보건복지부(장관 조규홍)와 한국보건산업진흥원(원장 차순도)은 3월 19일(수)병원-산업계 간 오픈이노베이션(개방형 혁신)을 촉진하기 위한 「개방형 실험실 운영」사업의 주관기관 6개 병원*을 신규 선정했다고 밝혔다. * (유형① 협업기반 조성형) 양산부산대학교병원",
  "path": "data/2025/2025-03/2025-03-19/060_보건복지부_개방형_실험실_운영_사업_주관기관_신규_선정.md"
}