{
  "id": "press-2025-06-18-065_조달청_조달청_차장_한국행정학회_하계학술대회_개회식_축사-1b772d2984",
  "detailPath": "docs/details/press/press-2025-06-18-065_조달청_조달청_차장_한국행정학회_하계학술대회_개회식_축사-1b772d2984.json",
  "layer": "press",
  "file": "065_조달청_조달청_차장_한국행정학회_하계학술대회_개회식_축사.md",
  "title": "조달청 차장, 한국행정학회 하계학술대회 개회식 축사",
  "institution": "조달청",
  "ministry": "조달청",
  "date": "2025-06-18",
  "approveDate": "06/18/2025 14:34:29",
  "docType": "brief",
  "groupingCode": "brief",
  "newsItemId": "156718110",
  "originalUrl": "https://www.korea.kr/briefing/pressReleaseView.do?newsId=156718110&call_from=openData",
  "source": "policy-briefing-api",
  "excerpt": "▶백승보 조달청 차장(단상)이 18일 오후 세종공동캠퍼스에서 열린 '2025 한국행정학회 하계학술대회'에 참석해 개회식 축사를 하고 있다. ▶백승보 조달청 차장(단상)이 18일 오후 세종공동캠퍼스에서 열린 '2025년 한국행정학회 하계공동학술대회 및 국제학술대회'에서 축사를 하고 있다. 이번 학술대회는 'K-행정의 진화와 성과 그리고 미래'를 주제로 6월 18일부터 20일까지 개최된다. *문",
  "path": "data/2025/2025-06/2025-06-18/065_조달청_조달청_차장_한국행정학회_하계학술대회_개회식_축사.md"
}