{
  "id": "press-2025-11-17-096_국무조정실_보도자료_제2차_부동산_불법행위_대응_협의회_보도자료-9c938179e5",
  "detailPath": "docs/details/press/press-2025-11-17-096_국무조정실_보도자료_제2차_부동산_불법행위_대응_협의회_보도자료-9c938179e5.json",
  "layer": "press",
  "file": "096_국무조정실_보도자료_제2차_부동산_불법행위_대응_협의회_보도자료.md",
  "title": "[보도자료] 제2차 부동산 불법행위 대응 협의회 보도자료",
  "institution": "국무조정실",
  "ministry": "국무조정실",
  "date": "2025-11-17",
  "approveDate": "11/17/2025 16:30:00",
  "docType": "brief",
  "groupingCode": "brief",
  "newsItemId": "156728706",
  "originalUrl": "https://www.korea.kr/briefing/pressReleaseView.do?newsId=156728706&call_from=openData",
  "source": "policy-briefing-api",
  "excerpt": "제2차 부동산 불법행위 대응 협의회 개최 - 외국인 주택 이상거래 기획조사 결과* 등 각 부처별 추진상황 등 점검 - 외국인 위법행위 법적제재 상향, 외국 탈세혐의 본국 통보 등 최고수위 엄중조치 추진 * 외국인 주택 이상거래('24.6~'25.5 거래신고분) 기획조사를 통해 위법 의심거래 210건(위법 의심행위 290건) 적발 / 해외자금 불법반입, 무자격비자 임대업, 편법증여 등 중점 점",
  "path": "data/2025/2025-11/2025-11-17/096_국무조정실_보도자료_제2차_부동산_불법행위_대응_협의회_보도자료.md"
}