{
  "id": "press-2025-02-12-028_국가유산청_조선시대_국왕의_능행을_심층_분석하다-75bc6180ed",
  "detailPath": "docs/details/press/press-2025-02-12-028_국가유산청_조선시대_국왕의_능행을_심층_분석하다-75bc6180ed.json",
  "layer": "press",
  "file": "028_국가유산청_조선시대_국왕의_능행을_심층_분석하다.md",
  "title": "조선시대 국왕의 능행을 심층 분석하다",
  "institution": "국가유산청",
  "ministry": "국가유산청",
  "date": "2025-02-12",
  "approveDate": "02/12/2025 09:21:45",
  "docType": "brief",
  "groupingCode": "brief",
  "newsItemId": "156673907",
  "originalUrl": "https://www.korea.kr/briefing/pressReleaseView.do?newsId=156673907&call_from=openData",
  "source": "policy-briefing-api",
  "excerpt": "국가유산청 궁능유적본부(본부장 이재필)는 조선시대 국왕이 선대 왕이나 왕비의 능에 제사를 지내거나 참배하기 위해 행차하는 '능행(陵幸)'의 실체를 규명하기 위해 지난해 진행한 심화 연구의 성과를 담은 보고서를 국가유산청과 궁능유적본부 누리집을 통해 공개하였다. * 국가유산청 누리집(https://www.khs.go.kr), 궁능유적본부 누리집(https://royal.khs.go.kr) 이번",
  "path": "data/2025/2025-02/2025-02-12/028_국가유산청_조선시대_국왕의_능행을_심층_분석하다.md"
}