{
  "id": "press-2025-07-15-025_국민권익위원회_고충_해결부터_소상공인_경영_상담까지_달리는_국민신문고_전국_순회_중",
  "detailPath": "docs/details/press/press-2025-07-15-025_국민권익위원회_고충_해결부터_소상공인_경영_상담까지_달리는_국민신문고_전국_순회_중.json",
  "layer": "press",
  "file": "025_국민권익위원회_고충_해결부터_소상공인_경영_상담까지_달리는_국민신문고_전국_순회_중.md",
  "title": "&quot;고충 해결부터 소상공인 경영 상담까지&quot;… '달리는 국민신문고' 전국 순회 중!",
  "institution": "국민권익위원회",
  "ministry": "국민권익위원회",
  "date": "2025-07-15",
  "approveDate": "07/15/2025 09:50:21",
  "docType": "brief",
  "groupingCode": "brief",
  "newsItemId": "156712374",
  "originalUrl": "https://www.korea.kr/briefing/pressReleaseView.do?newsId=156712374&call_from=openData",
  "source": "policy-briefing-api",
  "excerpt": "\"고충 해결부터 소상공인 경영 상담까지\"… '달리는 국민신문고' 전국 순회 중! - 국민권익위, 경남 창원시(7.16.)·창녕군(7.17.)·경북 상주시(7.18.) 방문 □ 경상남도 창원시와 창녕군, 경상북도 상주시에서 경기침체로 어려움을 겪고 있는 소상공인과 지역주민의 고충을 듣는 자리가 마련된다.",
  "path": "data/2025/2025-07/2025-07-15/025_국민권익위원회_고충_해결부터_소상공인_경영_상담까지_달리는_국민신문고_전국_순회_중.md"
}