{
  "id": "press-2025-01-07-011_국민권익위원회_읍_면지역까지_전국_방방곡곡_달리는_국민신문고에서_해결하세요-4a29a20d16",
  "detailPath": "docs/details/press/press-2025-01-07-011_국민권익위원회_읍_면지역까지_전국_방방곡곡_달리는_국민신문고에서_해결하세요-4a29a20d16.json",
  "layer": "press",
  "file": "011_국민권익위원회_읍_면지역까지_전국_방방곡곡_달리는_국민신문고에서_해결하세요.md",
  "title": "읍&middot;면지역까지 ‘전국 방방곡곡’… 달리는 국민신문고에서 해결하세요!",
  "institution": "국민권익위원회",
  "ministry": "국민권익위원회",
  "date": "2025-01-07",
  "approveDate": "01/07/2025 09:08:23",
  "docType": "brief",
  "groupingCode": "brief",
  "newsItemId": "156669190",
  "originalUrl": "https://www.korea.kr/briefing/pressReleaseView.do?newsId=156669190&call_from=openData",
  "source": "policy-briefing-api",
  "excerpt": "읍·면지역까지 ‘전국 방방곡곡’… 달리는 국민신문고에서 해결하세요! - 국민권익위, 경남 밀양시(8일)·경북 청도군(9일)·충북 보은군(10일) 방문 □ 경상남도 밀양시, 경상북도 청도군, 충청북도 보은군의 읍·면지역을 찾아가 어려움을 겪고 있는 소상공인 등 지역주민들의 고충을 듣는 자리가 마련된다.",
  "path": "data/2025/2025-01/2025-01-07/011_국민권익위원회_읍_면지역까지_전국_방방곡곡_달리는_국민신문고에서_해결하세요.md"
}