{
  "id": "press-2025-04-30-072_중소벤처기업부_중소기업제품_24년_공공구매액_131조원_달성-5108cbb4bd",
  "detailPath": "docs/details/press/press-2025-04-30-072_중소벤처기업부_중소기업제품_24년_공공구매액_131조원_달성-5108cbb4bd.json",
  "layer": "press",
  "file": "072_중소벤처기업부_중소기업제품_24년_공공구매액_131조원_달성.md",
  "title": "중소기업제품 24년 공공구매액 131조원 달성",
  "institution": "중소벤처기업부",
  "ministry": "중소벤처기업부",
  "date": "2025-04-30",
  "approveDate": "04/30/2025 11:27:40",
  "docType": "brief",
  "groupingCode": "brief",
  "newsItemId": "156687011",
  "originalUrl": "https://www.korea.kr/briefing/pressReleaseView.do?newsId=156687011&call_from=openData",
  "source": "policy-briefing-api",
  "excerpt": "공공기관이 '24년 구매한 중소기업제품의 총액이 역대 최대를 기록했다. 중소벤처기업부(장관 오영주, 이하 중기부)는 29일(화) 국무회의에서 2024년 공공기관의 중소기업제품 구매금액이 131조원(당초 계획 119.1조원)에 달한다고 밝혔다. 이는 공공구매제도 시행(2006년) 이후 사상 최대 구매액이다. 개별 공공기관*은 「중소기업제품 구매촉진 및 판로지원에 관한 법률(이하 판로지원법)」제",
  "path": "data/2025/2025-04/2025-04-30/072_중소벤처기업부_중소기업제품_24년_공공구매액_131조원_달성.md"
}