{
  "id": "press-2026-01-05-028_농림축산식품부_국민이_선택한_이름_시드큐브_국가_종자_관리의_기준이_되다-a7ee9bedcb",
  "detailPath": "docs/details/press/press-2026-01-05-028_농림축산식품부_국민이_선택한_이름_시드큐브_국가_종자_관리의_기준이_되다-a7ee9bedcb.json",
  "layer": "press",
  "file": "028_농림축산식품부_국민이_선택한_이름_시드큐브_국가_종자_관리의_기준이_되다.md",
  "title": "국민이 선택한 이름 '시드큐브', 국가 종자 관리의 기준이 되다",
  "institution": "농림축산식품부",
  "ministry": "농림축산식품부",
  "date": "2026-01-05",
  "approveDate": "01/05/2026 11:00:00",
  "docType": "brief",
  "groupingCode": "brief",
  "newsItemId": "156738081",
  "originalUrl": "https://www.korea.kr/briefing/pressReleaseView.do?newsId=156738081&call_from=openData",
  "source": "policy-briefing-api",
  "excerpt": "국립종자원(원장 양주필)은 종자검정연구센터 내 종자저장고의 공식 명칭을 '시드큐브(Seed Cube)'로 확정했다. 이번 명칭은 국민과 함께 정책을 만들어간다는 취지 아래, 2주간 진행된 온라인 국민참여 투표를 통해 최종 결정되었다. '시드큐브'는 씨앗(Seed)이 가진 생명의 가능성을 가장 안정적이고 완결된 구조인 큐브(Cube)에 담아 미래 세대까지 안전하게 이어간다는 의미를 담고 있다.",
  "path": "data/2026/2026-01/2026-01-05/028_농림축산식품부_국민이_선택한_이름_시드큐브_국가_종자_관리의_기준이_되다.md"
}