{
  "id": "press-2026-02-11-100_산림청_연_150톤_전시원_부산물_천연_퇴비화_로_처리비용_줄이고_환경_살린다",
  "detailPath": "docs/details/press/press-2026-02-11-100_산림청_연_150톤_전시원_부산물_천연_퇴비화_로_처리비용_줄이고_환경_살린다.json",
  "layer": "press",
  "file": "100_산림청_연_150톤_전시원_부산물_천연_퇴비화_로_처리비용_줄이고_환경_살린다.md",
  "title": "연 150톤 전시원 부산물, '천연 퇴비화'로 처리비용 줄이고 환경 살린다",
  "institution": "산림청",
  "ministry": "산림청",
  "date": "2026-02-11",
  "approveDate": "02/11/2026 14:20:13",
  "docType": "brief",
  "groupingCode": "brief",
  "newsItemId": "156744233",
  "originalUrl": "https://www.korea.kr/briefing/pressReleaseView.do?newsId=156744233&call_from=openData",
  "source": "policy-briefing-api",
  "excerpt": "- 산림청 국립수목원, 골칫거리 전시원 부산물을 자원으로 전환하는 퇴비화 성과 확인 - 산림청 국립수목원(원장 임영석)은 수목원 전시원을 관리하는 과정에서 발생하던 잡초와 낙엽 등 부산물을 활용해, 안전하고 영양가 높은 천연 퇴비를 생산하는 방법을 과학적으로 입증했다고 밝혔다. 국립수목원은 현재 25개의 전문 전시원을 관리하고 있으며, 이 과정에서 매년 약 150톤의 잡초와 낙엽이 발생한다.",
  "path": "data/2026/2026-02/2026-02-11/100_산림청_연_150톤_전시원_부산물_천연_퇴비화_로_처리비용_줄이고_환경_살린다.md"
}