{
  "id": "press-2025-07-23-064_병무청_병무청_집중호우_피해_관련_병역의무_이행일자_연기_및_병력동원훈련_면제-65ad9c7fd8",
  "detailPath": "docs/details/press/press-2025-07-23-064_병무청_병무청_집중호우_피해_관련_병역의무_이행일자_연기_및_병력동원훈련_면제-65ad9c7fd8.json",
  "layer": "press",
  "file": "064_병무청_병무청_집중호우_피해_관련_병역의무_이행일자_연기_및_병력동원훈련_면제.md",
  "title": "병무청, 집중호우 피해 관련 병역의무 이행일자 연기 및 병력동원훈련 면제",
  "institution": "병무청",
  "ministry": "병무청",
  "date": "2025-07-23",
  "approveDate": "07/23/2025 13:42:01",
  "docType": "brief",
  "groupingCode": "brief",
  "newsItemId": "156714821",
  "originalUrl": "https://www.korea.kr/briefing/pressReleaseView.do?newsId=156714821&call_from=openData",
  "source": "policy-briefing-api",
  "excerpt": "□ 병무청(청장 홍소영)은 7월 22일 집중호우 피해로 경기 가평, 충남 서산·예산, 전남 담양, 경남 산청·합천이 특별재난지역으로 선포됨에 따라 해당 지역에 거주하는 병역의무자 본인 또는 가족 등이 피해를 입은 경우 다음과 같이 병역의무 이행일자 연기 및 동원훈련 면제가 가능하다고 밝혔다. ○ 병역의무 이행일자 연기는 병역판정검사, 현역병 입영, 사회복무요원·대체복무요원·병력동원훈련 소집 ",
  "path": "data/2025/2025-07/2025-07-23/064_병무청_병무청_집중호우_피해_관련_병역의무_이행일자_연기_및_병력동원훈련_면제.md"
}