{
  "id": "press-2026-03-04-074_기후에너지환경부_성장형_탄소중립_달성을_위한_기후테크_혁신_연합_출범",
  "detailPath": "docs/details/press/press-2026-03-04-074_기후에너지환경부_성장형_탄소중립_달성을_위한_기후테크_혁신_연합_출범.json",
  "layer": "press",
  "file": "074_기후에너지환경부_성장형_탄소중립_달성을_위한_기후테크_혁신_연합_출범.md",
  "title": "성장형 탄소중립 달성을 위한 기후테크 혁신 연합 출범",
  "institution": "기후에너지환경부",
  "ministry": "기후에너지환경부",
  "date": "2026-03-04",
  "approveDate": "03/04/2026 14:00:00",
  "docType": "brief",
  "groupingCode": "brief",
  "newsItemId": "156747207",
  "originalUrl": "https://www.korea.kr/briefing/pressReleaseView.do?newsId=156747207&call_from=openData",
  "source": "policy-briefing-api",
  "excerpt": "▷ 혁신기업, 기후부-중기부, 공공기관이 참여하는 민관 정책 소통창구로 출범 ▷ 상시 운영을 통해 기후테크 산업 육성 대책 마련 추진 기후에너지환경부(장관 김성환)는 중소벤처기업부(장관 한성숙)와 공동으로 3월 4일 오후 마포디캠프(서울 마포구 소재)에서 기후테크업 육성을 위한 정부-공공기관-기업 간 상시 소통창구인 '기후테크 혁신 연합' 출범식을 개최한다고 밝혔다. 이날 출범식에는 주요 기",
  "path": "data/2026/2026-03/2026-03-04/074_기후에너지환경부_성장형_탄소중립_달성을_위한_기후테크_혁신_연합_출범.md"
}