{
  "layer": "gazette",
  "page": 169,
  "pageSize": 100,
  "totalItems": 48614,
  "totalPages": 487,
  "items": [
    {
      "id": "gazette-2024-10-18-054_산업통상자원부_국가기술표준원고시제2024_0424호_한국산업표준_확인-9c6d5b40d5",
      "layer": "gazette",
      "title": "국가기술표준원고시제2024-0424호(한국산업표준 확인)",
      "institution": "산업통상자원부",
      "date": "2024-10-18",
      "docType": "고시",
      "excerpt": "",
      "detailPath": "docs/details/gazette/gazette-2024-10-18-054_산업통상자원부_국가기술표준원고시제2024_0424호_한국산업표준_확인-9c6d5b40d5.json"
    },
    {
      "id": "gazette-2024-10-18-055_산업통상자원부_국가기술표준원고시제2024_0425호_한국산업표준_폐지_예고-09cbec0a5c",
      "layer": "gazette",
      "title": "국가기술표준원고시제2024-0425호(한국산업표준 폐지 예고)",
      "institution": "산업통상자원부",
      "date": "2024-10-18",
      "docType": "고시",
      "excerpt": "",
      "detailPath": "docs/details/gazette/gazette-2024-10-18-055_산업통상자원부_국가기술표준원고시제2024_0425호_한국산업표준_폐지_예고-09cbec0a5c.json"
    },
    {
      "id": "gazette-2024-10-18-056_산업통상자원부_국가기술표준원고시제2024_0426호_한국산업표준_제정_예고-43d436034d",
      "layer": "gazette",
      "title": "국가기술표준원고시제2024-0426호(한국산업표준 제정 예고)",
      "institution": "산업통상자원부",
      "date": "2024-10-18",
      "docType": "고시",
      "excerpt": "",
      "detailPath": "docs/details/gazette/gazette-2024-10-18-056_산업통상자원부_국가기술표준원고시제2024_0426호_한국산업표준_제정_예고-43d436034d.json"
    },
    {
      "id": "gazette-2024-10-18-057_산업통상자원부_국가기술표준원고시제2024_0459호_한국산업표준_확인-cdb31c5bd5",
      "layer": "gazette",
      "title": "국가기술표준원고시제2024-0459호(한국산업표준 확인)",
      "institution": "산업통상자원부",
      "date": "2024-10-18",
      "docType": "고시",
      "excerpt": "",
      "detailPath": "docs/details/gazette/gazette-2024-10-18-057_산업통상자원부_국가기술표준원고시제2024_0459호_한국산업표준_확인-cdb31c5bd5.json"
    },
    {
      "id": "gazette-2024-10-18-058_산업통상자원부_국가기술표준원고시제2024_0449호_한국산업표준_제정_고시_KSF2370-a86101f307",
      "layer": "gazette",
      "title": "국가기술표준원고시제2024-0449호(한국산업표준 제정 고시(KSF2370))",
      "institution": "산업통상자원부",
      "date": "2024-10-18",
      "docType": "고시",
      "excerpt": "",
      "detailPath": "docs/details/gazette/gazette-2024-10-18-058_산업통상자원부_국가기술표준원고시제2024_0449호_한국산업표준_제정_고시_KSF2370-a86101f307.json"
    },
    {
      "id": "gazette-2024-10-18-059_산업통상자원부_산업통상자원부공고제2024_732호_집단에너지_사업허가대상자_선정기준_전부개정고시안_행정예고-c6ad23a355",
      "layer": "gazette",
      "title": "산업통상자원부공고제2024-732호(｢집단에너지 사업허가대상자 선정기준｣ 전부개정고시안 행정예고)",
      "institution": "산업통상자원부",
      "date": "2024-10-18",
      "docType": "공고",
      "excerpt": "",
      "detailPath": "docs/details/gazette/gazette-2024-10-18-059_산업통상자원부_산업통상자원부공고제2024_732호_집단에너지_사업허가대상자_선정기준_전부개정고시안_행정예고-c6ad23a355.json"
    },
    {
      "id": "gazette-2024-10-18-060_식품의약품안전처_식품의약품안전처공고제2024_480호_임시마약류_지정_공고-4b1617fa56",
      "layer": "gazette",
      "title": "식품의약품안전처공고제2024-480호(임시마약류 지정 공고)",
      "institution": "식품의약품안전처",
      "date": "2024-10-18",
      "docType": "공고",
      "excerpt": "",
      "detailPath": "docs/details/gazette/gazette-2024-10-18-060_식품의약품안전처_식품의약품안전처공고제2024_480호_임시마약류_지정_공고-4b1617fa56.json"
    },
    {
      "id": "gazette-2024-10-18-061_식품의약품안전처_경인지방식품의약품안전청공고제2024_101호_수입식품법_위반업체_과태료_처분_사전통지_공고-225eebe4d0",
      "layer": "gazette",
      "title": "경인지방식품의약품안전청공고제2024-101호(수입식품법 위반업체 과태료 처분 사전통지 공고)",
      "institution": "식품의약품안전처",
      "date": "2024-10-18",
      "docType": "공고",
      "excerpt": "",
      "detailPath": "docs/details/gazette/gazette-2024-10-18-061_식품의약품안전처_경인지방식품의약품안전청공고제2024_101호_수입식품법_위반업체_과태료_처분_사전통지_공고-225eebe4d0.json"
    },
    {
      "id": "gazette-2024-10-18-062_여성가족부_여성가족부고시제2024_40호_청소년유해매체물_간행물_고시-3836c22121",
      "layer": "gazette",
      "title": "여성가족부고시제2024-40호(청소년유해매체물(간행물) 고시)",
      "institution": "여성가족부",
      "date": "2024-10-18",
      "docType": "고시",
      "excerpt": "",
      "detailPath": "docs/details/gazette/gazette-2024-10-18-062_여성가족부_여성가족부고시제2024_40호_청소년유해매체물_간행물_고시-3836c22121.json"
    },
    {
      "id": "gazette-2024-10-18-063_외교부_조약제697호_조약법에_관한_비엔나_협약_중_정정-3e44dfc13e",
      "layer": "gazette",
      "title": "조약제697호(조약법에 관한 비엔나 협약 중  정정)",
      "institution": "외교부",
      "date": "2024-10-18",
      "docType": "조약",
      "excerpt": "",
      "detailPath": "docs/details/gazette/gazette-2024-10-18-063_외교부_조약제697호_조약법에_관한_비엔나_협약_중_정정-3e44dfc13e.json"
    },
    {
      "id": "gazette-2024-10-18-064_외교부_조약제1059호_국제연합헌장_및_국제사법재판소규정_중_정정-bcd6a8d553",
      "layer": "gazette",
      "title": "조약제1059호(국제연합헌장 및 국제사법재판소규정 중 정정)",
      "institution": "외교부",
      "date": "2024-10-18",
      "docType": "조약",
      "excerpt": "",
      "detailPath": "docs/details/gazette/gazette-2024-10-18-064_외교부_조약제1059호_국제연합헌장_및_국제사법재판소규정_중_정정-bcd6a8d553.json"
    },
    {
      "id": "gazette-2024-10-18-065_정부산하기관및위원회_대차대조표_한국은행-d47b8224cc",
      "layer": "gazette",
      "title": "대차대조표(한국은행)",
      "institution": "정부산하기관및위원회",
      "date": "2024-10-18",
      "docType": "기타",
      "excerpt": "",
      "detailPath": "docs/details/gazette/gazette-2024-10-18-065_정부산하기관및위원회_대차대조표_한국은행-d47b8224cc.json"
    },
    {
      "id": "gazette-2024-10-18-066_중소벤처기업부_중소벤처기업부고시제2024_78호_서적_신문_및_잡지류_소매업_생계형_적합업종_지정_고시-eafce636fd",
      "layer": "gazette",
      "title": "중소벤처기업부고시제2024-78호(「서적, 신문 및 잡지류 소매업」 생계형 적합업종 지정 고시)",
      "institution": "중소벤처기업부",
      "date": "2024-10-18",
      "docType": "고시",
      "excerpt": "",
      "detailPath": "docs/details/gazette/gazette-2024-10-18-066_중소벤처기업부_중소벤처기업부고시제2024_78호_서적_신문_및_잡지류_소매업_생계형_적합업종_지정_고시-eafce636fd.json"
    },
    {
      "id": "gazette-2024-10-18-067_중소벤처기업부_중소벤처기업부고시제2024_76호_규제자유특구_지정_변경-7e9c92bcb1",
      "layer": "gazette",
      "title": "중소벤처기업부고시제2024-76호(규제자유특구 지정 변경)",
      "institution": "중소벤처기업부",
      "date": "2024-10-18",
      "docType": "고시",
      "excerpt": "",
      "detailPath": "docs/details/gazette/gazette-2024-10-18-067_중소벤처기업부_중소벤처기업부고시제2024_76호_규제자유특구_지정_변경-7e9c92bcb1.json"
    },
    {
      "id": "gazette-2024-10-18-068_충청남도_충청남도고시제2024_474호_충남도청_내포_신도시_개발사업_에_따른_개발계획_24차_및_실시계획_22차_변경_승-06ae933431",
      "layer": "gazette",
      "title": "충청남도고시제2024-474호(｢충남도청(내포) 신도시 개발사업｣에 따른 개발계획(24차) 및 실시계획(22차) 변경 승인, 도시관리계획(지구단위계획) 지형도면 고시)",
      "institution": "충청남도",
      "date": "2024-10-18",
      "docType": "지방자치단체",
      "excerpt": "",
      "detailPath": "docs/details/gazette/gazette-2024-10-18-068_충청남도_충청남도고시제2024_474호_충남도청_내포_신도시_개발사업_에_따른_개발계획_24차_및_실시계획_22차_변경_승-06ae933431.json"
    },
    {
      "id": "gazette-2024-10-18-069_충청남도교육청_충남온라인학교공고제2024_1호_관인_공인_등록-278204cc1b",
      "layer": "gazette",
      "title": "충남온라인학교공고제2024-1호(관인(공인)등록)",
      "institution": "충청남도교육청",
      "date": "2024-10-18",
      "docType": "기타",
      "excerpt": "",
      "detailPath": "docs/details/gazette/gazette-2024-10-18-069_충청남도교육청_충남온라인학교공고제2024_1호_관인_공인_등록-278204cc1b.json"
    },
    {
      "id": "gazette-2024-10-18-070_해양수산부_국립해양조사원공고제2024_61호_해양조사_정보업_등록_공고-45e7f9610a",
      "layer": "gazette",
      "title": "국립해양조사원공고제2024-61호(해양조사·정보업 등록 공고)",
      "institution": "해양수산부",
      "date": "2024-10-18",
      "docType": "공고",
      "excerpt": "",
      "detailPath": "docs/details/gazette/gazette-2024-10-18-070_해양수산부_국립해양조사원공고제2024_61호_해양조사_정보업_등록_공고-45e7f9610a.json"
    },
    {
      "id": "gazette-2024-10-18-071_해양수산부_대산지방해양수산청고시제2024_28호_사설항로표지_폐지_알림-bdb4175dcb",
      "layer": "gazette",
      "title": "대산지방해양수산청고시제2024-28호(사설항로표지 폐지 알림)",
      "institution": "해양수산부",
      "date": "2024-10-18",
      "docType": "고시",
      "excerpt": "",
      "detailPath": "docs/details/gazette/gazette-2024-10-18-071_해양수산부_대산지방해양수산청고시제2024_28호_사설항로표지_폐지_알림-bdb4175dcb.json"
    },
    {
      "id": "gazette-2024-10-18-072_해양수산부_해양수산부공고제2024_1043호_항만기술산업의_육성_및_지원에_관한_법률_시행규칙_제정령안_입법예고-c15b1908d2",
      "layer": "gazette",
      "title": "해양수산부공고제2024-1043호(항만기술산업의 육성 및 지원에 관한 법률 시행규칙 제정령안 입법예고)",
      "institution": "해양수산부",
      "date": "2024-10-18",
      "docType": "공고",
      "excerpt": "",
      "detailPath": "docs/details/gazette/gazette-2024-10-18-072_해양수산부_해양수산부공고제2024_1043호_항만기술산업의_육성_및_지원에_관한_법률_시행규칙_제정령안_입법예고-c15b1908d2.json"
    },
    {
      "id": "gazette-2024-10-18-073_해양수산부_해양수산부공고제2024_1044호_항만기술산업의_육성_및_지원에_관한_법률_시행령_제정령안_입법예고-c1c739950e",
      "layer": "gazette",
      "title": "해양수산부공고제2024-1044호(항만기술산업의 육성 및 지원에 관한 법률 시행령 제정령안 입법예고)",
      "institution": "해양수산부",
      "date": "2024-10-18",
      "docType": "공고",
      "excerpt": "",
      "detailPath": "docs/details/gazette/gazette-2024-10-18-073_해양수산부_해양수산부공고제2024_1044호_항만기술산업의_육성_및_지원에_관한_법률_시행령_제정령안_입법예고-c1c739950e.json"
    },
    {
      "id": "gazette-2024-10-18-074_행정안전부_행정안전부공고제2024_1421호_행정기관_IC카드_표준규격_폐지안_행정예고-b1b71c528b",
      "layer": "gazette",
      "title": "행정안전부공고제2024-1421호(「행정기관 IC카드 표준규격」폐지안 행정예고)",
      "institution": "행정안전부",
      "date": "2024-10-18",
      "docType": "공고",
      "excerpt": "",
      "detailPath": "docs/details/gazette/gazette-2024-10-18-074_행정안전부_행정안전부공고제2024_1421호_행정기관_IC카드_표준규격_폐지안_행정예고-b1b71c528b.json"
    },
    {
      "id": "gazette-2024-10-18-075_행정안전부_대통령공고제351호_특별재난지역_선포-4cd7baf49a",
      "layer": "gazette",
      "title": "대통령공고제351호(특별재난지역 선포)",
      "institution": "행정안전부",
      "date": "2024-10-18",
      "docType": "공고",
      "excerpt": "",
      "detailPath": "docs/details/gazette/gazette-2024-10-18-075_행정안전부_대통령공고제351호_특별재난지역_선포-4cd7baf49a.json"
    },
    {
      "id": "gazette-2024-10-18-076_행정안전부_행정안전부공고제2024_1427호_새마을금고법_시행규칙_일부개정령안_입법예고-b44ae21480",
      "layer": "gazette",
      "title": "행정안전부공고제2024-1427호(새마을금고법 시행규칙 일부개정령안 입법예고)",
      "institution": "행정안전부",
      "date": "2024-10-18",
      "docType": "공고",
      "excerpt": "",
      "detailPath": "docs/details/gazette/gazette-2024-10-18-076_행정안전부_행정안전부공고제2024_1427호_새마을금고법_시행규칙_일부개정령안_입법예고-b44ae21480.json"
    },
    {
      "id": "gazette-2024-10-18-077_행정안전부_행정안전부공고제2024_1441호_지방재정법_시행령_일부개정령안_입법예고-ee64a4aac9",
      "layer": "gazette",
      "title": "행정안전부공고제2024-1441호(지방재정법 시행령 일부개정령안 입법예고 )",
      "institution": "행정안전부",
      "date": "2024-10-18",
      "docType": "공고",
      "excerpt": "",
      "detailPath": "docs/details/gazette/gazette-2024-10-18-077_행정안전부_행정안전부공고제2024_1441호_지방재정법_시행령_일부개정령안_입법예고-ee64a4aac9.json"
    },
    {
      "id": "gazette-2024-10-18-078_환경부_영산강유역환경청고시제2024_41호_하천점용허가_고시-f50ba4691c",
      "layer": "gazette",
      "title": "영산강유역환경청고시제2024-41호(하천점용허가 고시)",
      "institution": "환경부",
      "date": "2024-10-18",
      "docType": "고시",
      "excerpt": "",
      "detailPath": "docs/details/gazette/gazette-2024-10-18-078_환경부_영산강유역환경청고시제2024_41호_하천점용허가_고시-f50ba4691c.json"
    },
    {
      "id": "gazette-2024-10-18-079_환경부_영산강유역환경청고시제2024_40호_하천공사_시행계획_고시_섬진강_임실1지구_하천정비사업-618bda0fa9",
      "layer": "gazette",
      "title": "영산강유역환경청고시제2024-40호(하천공사 시행계획 고시(섬진강 임실1지구 하천정비사업))",
      "institution": "환경부",
      "date": "2024-10-18",
      "docType": "고시",
      "excerpt": "",
      "detailPath": "docs/details/gazette/gazette-2024-10-18-079_환경부_영산강유역환경청고시제2024_40호_하천공사_시행계획_고시_섬진강_임실1지구_하천정비사업-618bda0fa9.json"
    },
    {
      "id": "gazette-2024-10-18-080_환경부_영산강유역환경청고시제2024_43호_하천공사_시행계획_고시_황룡강_황룡2지구_하천환경정비사업-80f8e6077c",
      "layer": "gazette",
      "title": "영산강유역환경청고시제2024-43호(하천공사 시행계획 고시(황룡강 황룡2지구 하천환경정비사업))",
      "institution": "환경부",
      "date": "2024-10-18",
      "docType": "고시",
      "excerpt": "",
      "detailPath": "docs/details/gazette/gazette-2024-10-18-080_환경부_영산강유역환경청고시제2024_43호_하천공사_시행계획_고시_황룡강_황룡2지구_하천환경정비사업-80f8e6077c.json"
    },
    {
      "id": "gazette-2024-10-18-081_환경부_영산강유역환경청고시제2024_42호_하천공사_시행계획_고시_황룡강_황룡1지구_하천환경정비사업-90e8533011",
      "layer": "gazette",
      "title": "영산강유역환경청고시제2024-42호(하천공사 시행계획 고시(황룡강 황룡1지구 하천환경정비사업))",
      "institution": "환경부",
      "date": "2024-10-18",
      "docType": "고시",
      "excerpt": "",
      "detailPath": "docs/details/gazette/gazette-2024-10-18-081_환경부_영산강유역환경청고시제2024_42호_하천공사_시행계획_고시_황룡강_황룡1지구_하천환경정비사업-90e8533011.json"
    },
    {
      "id": "gazette-2024-10-18-082_환경부_영산강유역환경청고시제2024_39호_하천공사_시행계획_고시_섬진강_임실2지구_하천정비사업-10ed4a8274",
      "layer": "gazette",
      "title": "영산강유역환경청고시제2024-39호(하천공사 시행계획 고시(섬진강 임실2지구 하천정비사업))",
      "institution": "환경부",
      "date": "2024-10-18",
      "docType": "고시",
      "excerpt": "",
      "detailPath": "docs/details/gazette/gazette-2024-10-18-082_환경부_영산강유역환경청고시제2024_39호_하천공사_시행계획_고시_섬진강_임실2지구_하천정비사업-10ed4a8274.json"
    },
    {
      "id": "gazette-2024-10-18-083_환경부_환경부령제1122호_제품의_포장재질_포장방법에_관한_기준_등에_관한_규칙_일부개정령-c3d943227e",
      "layer": "gazette",
      "title": "환경부령제1122호(제품의 포장재질ㆍ포장방법에 관한 기준 등에 관한 규칙 일부개정령)",
      "institution": "환경부",
      "date": "2024-10-18",
      "docType": "부령",
      "excerpt": "",
      "detailPath": "docs/details/gazette/gazette-2024-10-18-083_환경부_환경부령제1122호_제품의_포장재질_포장방법에_관한_기준_등에_관한_규칙_일부개정령-c3d943227e.json"
    },
    {
      "id": "gazette-2024-10-18-084_환경부_금강유역환경청고시제2024_519호_하천공사_시행계획_미호강_미잠지구-3700f6df63",
      "layer": "gazette",
      "title": "금강유역환경청고시제2024-519호(하천공사 시행계획(미호강 미잠지구))",
      "institution": "환경부",
      "date": "2024-10-18",
      "docType": "고시",
      "excerpt": "",
      "detailPath": "docs/details/gazette/gazette-2024-10-18-084_환경부_금강유역환경청고시제2024_519호_하천공사_시행계획_미호강_미잠지구-3700f6df63.json"
    },
    {
      "id": "gazette-2024-10-18-085_환경부_금강유역환경청고시제2024_518호_하천공사_시행계획_미호강_인산지구-316b5fc9db",
      "layer": "gazette",
      "title": "금강유역환경청고시제2024-518호(하천공사 시행계획(미호강 인산지구))",
      "institution": "환경부",
      "date": "2024-10-18",
      "docType": "고시",
      "excerpt": "",
      "detailPath": "docs/details/gazette/gazette-2024-10-18-085_환경부_금강유역환경청고시제2024_518호_하천공사_시행계획_미호강_인산지구-316b5fc9db.json"
    },
    {
      "id": "gazette-2024-10-18-086_환경부_금강유역환경청고시제2024_517호_하천공사_시행계획_미호강_구곡지구-07c2833877",
      "layer": "gazette",
      "title": "금강유역환경청고시제2024-517호(하천공사 시행계획(미호강 구곡지구))",
      "institution": "환경부",
      "date": "2024-10-18",
      "docType": "고시",
      "excerpt": "",
      "detailPath": "docs/details/gazette/gazette-2024-10-18-086_환경부_금강유역환경청고시제2024_517호_하천공사_시행계획_미호강_구곡지구-07c2833877.json"
    },
    {
      "id": "gazette-2024-10-21-001_경상남도교육청_경상남도사천교육지원청공고제2024_107호_개인과외교습자_직권폐지_예정_공시송달_공고-8b6303e2dd",
      "layer": "gazette",
      "title": "경상남도사천교육지원청공고제2024-107호(개인과외교습자 직권폐지(예정) 공시송달 공고)",
      "institution": "경상남도교육청",
      "date": "2024-10-21",
      "docType": "지방자치단체",
      "excerpt": "",
      "detailPath": "docs/details/gazette/gazette-2024-10-21-001_경상남도교육청_경상남도사천교육지원청공고제2024_107호_개인과외교습자_직권폐지_예정_공시송달_공고-8b6303e2dd.json"
    },
    {
      "id": "gazette-2024-10-21-002_경찰청_서울특별시경찰청공고제2024_29호_관인_공인_등록_폐기-53ce257347",
      "layer": "gazette",
      "title": "서울특별시경찰청공고제2024-29호(관인(공인)등록/폐기)",
      "institution": "경찰청",
      "date": "2024-10-21",
      "docType": "기타",
      "excerpt": "",
      "detailPath": "docs/details/gazette/gazette-2024-10-21-002_경찰청_서울특별시경찰청공고제2024_29호_관인_공인_등록_폐기-53ce257347.json"
    },
    {
      "id": "gazette-2024-10-21-003_경찰청_제주특별자치도경찰청공고제2024_45호_관인_공인_등록_폐기-d11b95a341",
      "layer": "gazette",
      "title": "제주특별자치도경찰청공고제2024-45호(관인(공인)등록/폐기)",
      "institution": "경찰청",
      "date": "2024-10-21",
      "docType": "기타",
      "excerpt": "",
      "detailPath": "docs/details/gazette/gazette-2024-10-21-003_경찰청_제주특별자치도경찰청공고제2024_45호_관인_공인_등록_폐기-d11b95a341.json"
    },
    {
      "id": "gazette-2024-10-21-004_고용노동부_인천북부지청공고제2024_63호_사회적기업_인증_반납_수리_공고-6cc26bdd04",
      "layer": "gazette",
      "title": "인천북부지청공고제2024-63호(사회적기업 인증 반납 수리 공고)",
      "institution": "고용노동부",
      "date": "2024-10-21",
      "docType": "공고",
      "excerpt": "",
      "detailPath": "docs/details/gazette/gazette-2024-10-21-004_고용노동부_인천북부지청공고제2024_63호_사회적기업_인증_반납_수리_공고-6cc26bdd04.json"
    },
    {
      "id": "gazette-2024-10-21-005_고용노동부_영월출장소공고제2024_20호_사회적기업_인증_반납_수리_공고-6a634240b1",
      "layer": "gazette",
      "title": "영월출장소공고제2024-20호(사회적기업 인증 반납 수리 공고)",
      "institution": "고용노동부",
      "date": "2024-10-21",
      "docType": "공고",
      "excerpt": "",
      "detailPath": "docs/details/gazette/gazette-2024-10-21-005_고용노동부_영월출장소공고제2024_20호_사회적기업_인증_반납_수리_공고-6a634240b1.json"
    },
    {
      "id": "gazette-2024-10-21-006_과학기술정보통신부_전주전파관리소공고제2024_59호_전파법령_위반_정기검사_불응_무선국_행정처분_전_청문통지-f0a15b05a2",
      "layer": "gazette",
      "title": "전주전파관리소공고제2024-59호(전파법령 위반(정기검사 불응) 무선국 행정처분 전 청문통지)",
      "institution": "과학기술정보통신부",
      "date": "2024-10-21",
      "docType": "공고",
      "excerpt": "",
      "detailPath": "docs/details/gazette/gazette-2024-10-21-006_과학기술정보통신부_전주전파관리소공고제2024_59호_전파법령_위반_정기검사_불응_무선국_행정처분_전_청문통지-f0a15b05a2.json"
    },
    {
      "id": "gazette-2024-10-21-007_국가보훈부_국가보훈부공고제2024_249호_5_18민주유공자예우_및_단체설립에_관한_법률_시행령_일부개정령안_재입법예고-a5affa4905",
      "layer": "gazette",
      "title": "국가보훈부공고제2024-249호(「5ㆍ18민주유공자예우 및 단체설립에 관한 법률 시행령」  일부개정령안 재입법예고)",
      "institution": "국가보훈부",
      "date": "2024-10-21",
      "docType": "공고",
      "excerpt": "",
      "detailPath": "docs/details/gazette/gazette-2024-10-21-007_국가보훈부_국가보훈부공고제2024_249호_5_18민주유공자예우_및_단체설립에_관한_법률_시행령_일부개정령안_재입법예고-a5affa4905.json"
    },
    {
      "id": "gazette-2024-10-21-008_국가보훈부_국가보훈부공고제2024_251호_보훈보상대상자_지원에_관한_법률_시행령_일부개정령안_재입법예고-ebd1c0ed27",
      "layer": "gazette",
      "title": "국가보훈부공고제2024-251호(「보훈보상대상자 지원에 관한 법률 시행령」  일부개정령안 재입법예고)",
      "institution": "국가보훈부",
      "date": "2024-10-21",
      "docType": "공고",
      "excerpt": "",
      "detailPath": "docs/details/gazette/gazette-2024-10-21-008_국가보훈부_국가보훈부공고제2024_251호_보훈보상대상자_지원에_관한_법률_시행령_일부개정령안_재입법예고-ebd1c0ed27.json"
    },
    {
      "id": "gazette-2024-10-21-009_국가보훈부_국가보훈부공고제2024_248호_국가유공자_등_예우_및_지원에_관한_법률_시행령_일부개정령안_재입법예고-7bf084103f",
      "layer": "gazette",
      "title": "국가보훈부공고제2024-248호(「국가유공자 등 예우 및 지원에 관한 법률 시행령」  일부개정령안 재입법예고)",
      "institution": "국가보훈부",
      "date": "2024-10-21",
      "docType": "공고",
      "excerpt": "",
      "detailPath": "docs/details/gazette/gazette-2024-10-21-009_국가보훈부_국가보훈부공고제2024_248호_국가유공자_등_예우_및_지원에_관한_법률_시행령_일부개정령안_재입법예고-7bf084103f.json"
    },
    {
      "id": "gazette-2024-10-21-010_국가보훈부_국가보훈부공고제2024_250호_특수임무유공자_예우_및_단체설립에_관한_법률_시행령_일부개정령안_재입법예고-0069af5c05",
      "layer": "gazette",
      "title": "국가보훈부공고제2024-250호(「특수임무유공자 예우 및 단체설립에 관한 법률 시행령」 일부개정령안 재입법예고)",
      "institution": "국가보훈부",
      "date": "2024-10-21",
      "docType": "공고",
      "excerpt": "",
      "detailPath": "docs/details/gazette/gazette-2024-10-21-010_국가보훈부_국가보훈부공고제2024_250호_특수임무유공자_예우_및_단체설립에_관한_법률_시행령_일부개정령안_재입법예고-0069af5c05.json"
    },
    {
      "id": "gazette-2024-10-21-011_국방부_보상결정의_공시_군사법원-1040f1e6f2",
      "layer": "gazette",
      "title": "보상결정의 공시(군사법원)",
      "institution": "국방부",
      "date": "2024-10-21",
      "docType": "기타",
      "excerpt": "",
      "detailPath": "docs/details/gazette/gazette-2024-10-21-011_국방부_보상결정의_공시_군사법원-1040f1e6f2.json"
    },
    {
      "id": "gazette-2024-10-21-012_국방부_국방부고시제2024_30호_국방_군사시설사업계획_승인-91e02f1d91",
      "layer": "gazette",
      "title": "국방부고시제2024-30호(국방ㆍ군사시설사업계획 승인)",
      "institution": "국방부",
      "date": "2024-10-21",
      "docType": "고시",
      "excerpt": "",
      "detailPath": "docs/details/gazette/gazette-2024-10-21-012_국방부_국방부고시제2024_30호_국방_군사시설사업계획_승인-91e02f1d91.json"
    },
    {
      "id": "gazette-2024-10-21-013_국토교통부_대전지방국토관리청고시제2024_125호_도로구역결정_변경_실효_고시-e3792ff923",
      "layer": "gazette",
      "title": "대전지방국토관리청고시제2024-125호(도로구역결정(변경) 실효 고시)",
      "institution": "국토교통부",
      "date": "2024-10-21",
      "docType": "고시",
      "excerpt": "",
      "detailPath": "docs/details/gazette/gazette-2024-10-21-013_국토교통부_대전지방국토관리청고시제2024_125호_도로구역결정_변경_실효_고시-e3792ff923.json"
    },
    {
      "id": "gazette-2024-10-21-014_국토교통부_부산지방항공청고시제2024_63호_비행장개발사업_준공확인_회전익_비행센터-0079bcf6cf",
      "layer": "gazette",
      "title": "부산지방항공청고시제2024-63호(비행장개발사업 준공확인(회전익 비행센터))",
      "institution": "국토교통부",
      "date": "2024-10-21",
      "docType": "고시",
      "excerpt": "",
      "detailPath": "docs/details/gazette/gazette-2024-10-21-014_국토교통부_부산지방항공청고시제2024_63호_비행장개발사업_준공확인_회전익_비행센터-0079bcf6cf.json"
    },
    {
      "id": "gazette-2024-10-21-015_국토교통부_서울지방국토관리청공고제2024_220호_행정처분_과태료_공고-4961569de2",
      "layer": "gazette",
      "title": "서울지방국토관리청공고제2024-220호(행정처분(과태료) 공고)",
      "institution": "국토교통부",
      "date": "2024-10-21",
      "docType": "공고",
      "excerpt": "",
      "detailPath": "docs/details/gazette/gazette-2024-10-21-015_국토교통부_서울지방국토관리청공고제2024_220호_행정처분_과태료_공고-4961569de2.json"
    },
    {
      "id": "gazette-2024-10-21-016_국토교통부_국토교통부고시제2024_548호_스마트도시_조성_위탁업무_및_수탁기관_지정_고시-88b825a696",
      "layer": "gazette",
      "title": "국토교통부고시제2024-548호(스마트도시 조성 위탁업무 및 수탁기관 지정 고시)",
      "institution": "국토교통부",
      "date": "2024-10-21",
      "docType": "고시",
      "excerpt": "",
      "detailPath": "docs/details/gazette/gazette-2024-10-21-016_국토교통부_국토교통부고시제2024_548호_스마트도시_조성_위탁업무_및_수탁기관_지정_고시-88b825a696.json"
    },
    {
      "id": "gazette-2024-10-21-017_금융위원회_금융위원회공고제2024_372호_합병_인가_공고-d3fa710708",
      "layer": "gazette",
      "title": "금융위원회공고제2024-372호(합병 인가 공고)",
      "institution": "금융위원회",
      "date": "2024-10-21",
      "docType": "공고",
      "excerpt": "",
      "detailPath": "docs/details/gazette/gazette-2024-10-21-017_금융위원회_금융위원회공고제2024_372호_합병_인가_공고-d3fa710708.json"
    },
    {
      "id": "gazette-2024-10-21-018_금융위원회_금융위원회공고제2024_374호_부수업무_신고_사실_공고_신한카드_주-931dffbf1e",
      "layer": "gazette",
      "title": "금융위원회공고제2024-374호(부수업무 신고 사실 공고 - 신한카드(주))",
      "institution": "금융위원회",
      "date": "2024-10-21",
      "docType": "공고",
      "excerpt": "",
      "detailPath": "docs/details/gazette/gazette-2024-10-21-018_금융위원회_금융위원회공고제2024_374호_부수업무_신고_사실_공고_신한카드_주-931dffbf1e.json"
    },
    {
      "id": "gazette-2024-10-21-019_농림축산식품부_농림축산식품부령제685호_농업_농촌_및_식품산업_기본법_시행규칙_일부개정령-b9b51378dd",
      "layer": "gazette",
      "title": "농림축산식품부령제685호(농업·농촌 및 식품산업 기본법 시행규칙 일부개정령)",
      "institution": "농림축산식품부",
      "date": "2024-10-21",
      "docType": "부령",
      "excerpt": "",
      "detailPath": "docs/details/gazette/gazette-2024-10-21-019_농림축산식품부_농림축산식품부령제685호_농업_농촌_및_식품산업_기본법_시행규칙_일부개정령-b9b51378dd.json"
    },
    {
      "id": "gazette-2024-10-21-020_대검찰청_기타_압수물환부공고_속초지청-435c372988",
      "layer": "gazette",
      "title": "기타(압수물환부공고 (속초지청))",
      "institution": "대검찰청",
      "date": "2024-10-21",
      "docType": "기타",
      "excerpt": "",
      "detailPath": "docs/details/gazette/gazette-2024-10-21-020_대검찰청_기타_압수물환부공고_속초지청-435c372988.json"
    },
    {
      "id": "gazette-2024-10-21-021_대검찰청_기타_압수물환부공고_전주지방검찰청-1da9f6efeb",
      "layer": "gazette",
      "title": "기타(압수물환부공고 (전주지방검찰청))",
      "institution": "대검찰청",
      "date": "2024-10-21",
      "docType": "기타",
      "excerpt": "",
      "detailPath": "docs/details/gazette/gazette-2024-10-21-021_대검찰청_기타_압수물환부공고_전주지방검찰청-1da9f6efeb.json"
    },
    {
      "id": "gazette-2024-10-21-022_대검찰청_기타_압수물환부공고_전주지방검찰청-ec54a96080",
      "layer": "gazette",
      "title": "기타(압수물환부공고 (전주지방검찰청))",
      "institution": "대검찰청",
      "date": "2024-10-21",
      "docType": "기타",
      "excerpt": "",
      "detailPath": "docs/details/gazette/gazette-2024-10-21-022_대검찰청_기타_압수물환부공고_전주지방검찰청-ec54a96080.json"
    },
    {
      "id": "gazette-2024-10-21-023_대법원_형사보상결정공시_속초지원-e4408d5539",
      "layer": "gazette",
      "title": "형사보상결정공시(속초지원)",
      "institution": "대법원",
      "date": "2024-10-21",
      "docType": "법원",
      "excerpt": "",
      "detailPath": "docs/details/gazette/gazette-2024-10-21-023_대법원_형사보상결정공시_속초지원-e4408d5539.json"
    },
    {
      "id": "gazette-2024-10-21-024_방송통신위원회_방송통신사무소공고제2024_114호_정보통신망_이용촉진_및_정보보호_등에_관한_법률_위반에_따른_과태료_처분-cd7b8ac3e9",
      "layer": "gazette",
      "title": "방송통신사무소공고제2024-114호(정보통신망 이용촉진 및 정보보호 등에 관한 법률 위반에 따른 과태료 처분 공시송달)",
      "institution": "방송통신위원회",
      "date": "2024-10-21",
      "docType": "공고",
      "excerpt": "",
      "detailPath": "docs/details/gazette/gazette-2024-10-21-024_방송통신위원회_방송통신사무소공고제2024_114호_정보통신망_이용촉진_및_정보보호_등에_관한_법률_위반에_따른_과태료_처분-cd7b8ac3e9.json"
    },
    {
      "id": "gazette-2024-10-21-025_법무부_안산출입국_외국인사무소고시제2024_39호_국적상실-66eb81d3db",
      "layer": "gazette",
      "title": "안산출입국.외국인사무소고시제2024-39호(국적상실)",
      "institution": "법무부",
      "date": "2024-10-21",
      "docType": "고시",
      "excerpt": "",
      "detailPath": "docs/details/gazette/gazette-2024-10-21-025_법무부_안산출입국_외국인사무소고시제2024_39호_국적상실-66eb81d3db.json"
    },
    {
      "id": "gazette-2024-10-21-026_법무부_수원출입국_외국인청고시제2024_57호_국적상실중정정-c1c30a8f8e",
      "layer": "gazette",
      "title": "수원출입국.외국인청고시제2024-57호(국적상실중정정)",
      "institution": "법무부",
      "date": "2024-10-21",
      "docType": "고시",
      "excerpt": "",
      "detailPath": "docs/details/gazette/gazette-2024-10-21-026_법무부_수원출입국_외국인청고시제2024_57호_국적상실중정정-c1c30a8f8e.json"
    },
    {
      "id": "gazette-2024-10-21-027_법무부_춘천출입국_외국인사무소고시제2024_43호_국적상실-5198004f91",
      "layer": "gazette",
      "title": "춘천출입국.외국인사무소고시제2024-43호(국적상실)",
      "institution": "법무부",
      "date": "2024-10-21",
      "docType": "고시",
      "excerpt": "",
      "detailPath": "docs/details/gazette/gazette-2024-10-21-027_법무부_춘천출입국_외국인사무소고시제2024_43호_국적상실-5198004f91.json"
    },
    {
      "id": "gazette-2024-10-21-028_법무부_부산출입국_외국인청고시제2024_0169호_국적상실-4902d6f7ec",
      "layer": "gazette",
      "title": "부산출입국.외국인청고시제2024-0169호(국적상실)",
      "institution": "법무부",
      "date": "2024-10-21",
      "docType": "고시",
      "excerpt": "",
      "detailPath": "docs/details/gazette/gazette-2024-10-21-028_법무부_부산출입국_외국인청고시제2024_0169호_국적상실-4902d6f7ec.json"
    },
    {
      "id": "gazette-2024-10-21-029_법무부_법무부고시제2024_481호_국적취득_귀화_중_취소-f85ac766f0",
      "layer": "gazette",
      "title": "법무부고시제2024-481호(국적취득(귀화) 중 취소)",
      "institution": "법무부",
      "date": "2024-10-21",
      "docType": "고시",
      "excerpt": "",
      "detailPath": "docs/details/gazette/gazette-2024-10-21-029_법무부_법무부고시제2024_481호_국적취득_귀화_중_취소-f85ac766f0.json"
    },
    {
      "id": "gazette-2024-10-21-030_법무부_법무부고시제2024_473호_국적취득_귀화_중_취소-65508eed41",
      "layer": "gazette",
      "title": "법무부고시제2024-473호(국적취득(귀화) 중 취소)",
      "institution": "법무부",
      "date": "2024-10-21",
      "docType": "고시",
      "excerpt": "",
      "detailPath": "docs/details/gazette/gazette-2024-10-21-030_법무부_법무부고시제2024_473호_국적취득_귀화_중_취소-65508eed41.json"
    },
    {
      "id": "gazette-2024-10-21-031_법무부_법무부고시제2024_474호_국적취득_귀화_중_취소-7be734520d",
      "layer": "gazette",
      "title": "법무부고시제2024-474호(국적취득(귀화) 중 취소)",
      "institution": "법무부",
      "date": "2024-10-21",
      "docType": "고시",
      "excerpt": "",
      "detailPath": "docs/details/gazette/gazette-2024-10-21-031_법무부_법무부고시제2024_474호_국적취득_귀화_중_취소-7be734520d.json"
    },
    {
      "id": "gazette-2024-10-21-032_법무부_법무부고시제2024_475호_국적취득_귀화_중_취소-838fe8b8f9",
      "layer": "gazette",
      "title": "법무부고시제2024-475호(국적취득(귀화) 중 취소)",
      "institution": "법무부",
      "date": "2024-10-21",
      "docType": "고시",
      "excerpt": "",
      "detailPath": "docs/details/gazette/gazette-2024-10-21-032_법무부_법무부고시제2024_475호_국적취득_귀화_중_취소-838fe8b8f9.json"
    },
    {
      "id": "gazette-2024-10-21-033_법무부_법무부고시제2024_476호_국적취득_귀화_중_취소-fcf1d63e16",
      "layer": "gazette",
      "title": "법무부고시제2024-476호(국적취득(귀화) 중 취소)",
      "institution": "법무부",
      "date": "2024-10-21",
      "docType": "고시",
      "excerpt": "",
      "detailPath": "docs/details/gazette/gazette-2024-10-21-033_법무부_법무부고시제2024_476호_국적취득_귀화_중_취소-fcf1d63e16.json"
    },
    {
      "id": "gazette-2024-10-21-034_법무부_법무부고시제2024_477호_국적취득_귀화_중_취소-ba5984b0b9",
      "layer": "gazette",
      "title": "법무부고시제2024-477호(국적취득(귀화) 중 취소)",
      "institution": "법무부",
      "date": "2024-10-21",
      "docType": "고시",
      "excerpt": "",
      "detailPath": "docs/details/gazette/gazette-2024-10-21-034_법무부_법무부고시제2024_477호_국적취득_귀화_중_취소-ba5984b0b9.json"
    },
    {
      "id": "gazette-2024-10-21-035_법무부_법무부고시제2024_478호_국적취득_귀화_중_취소-8aceb70c14",
      "layer": "gazette",
      "title": "법무부고시제2024-478호(국적취득(귀화) 중 취소)",
      "institution": "법무부",
      "date": "2024-10-21",
      "docType": "고시",
      "excerpt": "",
      "detailPath": "docs/details/gazette/gazette-2024-10-21-035_법무부_법무부고시제2024_478호_국적취득_귀화_중_취소-8aceb70c14.json"
    },
    {
      "id": "gazette-2024-10-21-036_법무부_법무부고시제2024_479호_국적취득_귀화_중_취소-8274b05e99",
      "layer": "gazette",
      "title": "법무부고시제2024-479호(국적취득(귀화) 중 취소)",
      "institution": "법무부",
      "date": "2024-10-21",
      "docType": "고시",
      "excerpt": "",
      "detailPath": "docs/details/gazette/gazette-2024-10-21-036_법무부_법무부고시제2024_479호_국적취득_귀화_중_취소-8274b05e99.json"
    },
    {
      "id": "gazette-2024-10-21-037_법무부_법무부고시제2024_480호_국적취득_귀화_중_취소-ea422fcdc2",
      "layer": "gazette",
      "title": "법무부고시제2024-480호(국적취득(귀화) 중 취소)",
      "institution": "법무부",
      "date": "2024-10-21",
      "docType": "고시",
      "excerpt": "",
      "detailPath": "docs/details/gazette/gazette-2024-10-21-037_법무부_법무부고시제2024_480호_국적취득_귀화_중_취소-ea422fcdc2.json"
    },
    {
      "id": "gazette-2024-10-21-038_보건복지부_보건복지부공고제2024_711호_아동복지법_시행규칙_일부개정령_안_입법예고-b7aae41750",
      "layer": "gazette",
      "title": "보건복지부공고제2024-711호(「아동복지법 시행규칙」일부개정령(안) 입법예고 )",
      "institution": "보건복지부",
      "date": "2024-10-21",
      "docType": "공고",
      "excerpt": "",
      "detailPath": "docs/details/gazette/gazette-2024-10-21-038_보건복지부_보건복지부공고제2024_711호_아동복지법_시행규칙_일부개정령_안_입법예고-b7aae41750.json"
    },
    {
      "id": "gazette-2024-10-21-039_산림청_국립자연휴양림관리소공고제2024_253호_국가채권_독촉장_공시송달-cec142d45b",
      "layer": "gazette",
      "title": "국립자연휴양림관리소공고제2024-253호(국가채권 독촉장 공시송달)",
      "institution": "산림청",
      "date": "2024-10-21",
      "docType": "공고",
      "excerpt": "",
      "detailPath": "docs/details/gazette/gazette-2024-10-21-039_산림청_국립자연휴양림관리소공고제2024_253호_국가채권_독촉장_공시송달-cec142d45b.json"
    },
    {
      "id": "gazette-2024-10-21-040_산업통상자원부_산업통상자원부고시제2024_161호_국가산업단지_서울디지털_등_27개_관리기본계획_일부개정-e0da6eecd6",
      "layer": "gazette",
      "title": "산업통상자원부고시제2024-161호(국가산업단지[서울디지털 등 27개] 관리기본계획 일부개정)",
      "institution": "산업통상자원부",
      "date": "2024-10-21",
      "docType": "고시",
      "excerpt": "",
      "detailPath": "docs/details/gazette/gazette-2024-10-21-040_산업통상자원부_산업통상자원부고시제2024_161호_국가산업단지_서울디지털_등_27개_관리기본계획_일부개정-e0da6eecd6.json"
    },
    {
      "id": "gazette-2024-10-21-041_산업통상자원부_국가기술표준원고시제2024_0436호_한국산업표준_제정_예고-535a5d191c",
      "layer": "gazette",
      "title": "국가기술표준원고시제2024-0436호(한국산업표준 제정 예고)",
      "institution": "산업통상자원부",
      "date": "2024-10-21",
      "docType": "고시",
      "excerpt": "",
      "detailPath": "docs/details/gazette/gazette-2024-10-21-041_산업통상자원부_국가기술표준원고시제2024_0436호_한국산업표준_제정_예고-535a5d191c.json"
    },
    {
      "id": "gazette-2024-10-21-042_산업통상자원부_국가기술표준원고시제2024_0437호_한국산업표준_개정-0bc45c4bbd",
      "layer": "gazette",
      "title": "국가기술표준원고시제2024-0437호(한국산업표준 개정)",
      "institution": "산업통상자원부",
      "date": "2024-10-21",
      "docType": "고시",
      "excerpt": "",
      "detailPath": "docs/details/gazette/gazette-2024-10-21-042_산업통상자원부_국가기술표준원고시제2024_0437호_한국산업표준_개정-0bc45c4bbd.json"
    },
    {
      "id": "gazette-2024-10-21-043_산업통상자원부_국가기술표준원고시제2024_0438호_한국산업표준_제정_고시_KSCIEC62715_1_1_등_4종-84f97147c5",
      "layer": "gazette",
      "title": "국가기술표준원고시제2024-0438호(한국산업표준 제정 고시(KSCIEC62715-1-1 등 4종))",
      "institution": "산업통상자원부",
      "date": "2024-10-21",
      "docType": "고시",
      "excerpt": "",
      "detailPath": "docs/details/gazette/gazette-2024-10-21-043_산업통상자원부_국가기술표준원고시제2024_0438호_한국산업표준_제정_고시_KSCIEC62715_1_1_등_4종-84f97147c5.json"
    },
    {
      "id": "gazette-2024-10-21-044_산업통상자원부_국가기술표준원고시제2024_0443호_한국산업표준_개정_고시-2b6c9347c1",
      "layer": "gazette",
      "title": "국가기술표준원고시제2024-0443호(한국산업표준 개정 고시)",
      "institution": "산업통상자원부",
      "date": "2024-10-21",
      "docType": "고시",
      "excerpt": "",
      "detailPath": "docs/details/gazette/gazette-2024-10-21-044_산업통상자원부_국가기술표준원고시제2024_0443호_한국산업표준_개정_고시-2b6c9347c1.json"
    },
    {
      "id": "gazette-2024-10-21-045_산업통상자원부_국가기술표준원고시제2024_0445호_한국산업표준_개정_예고-a521a0549d",
      "layer": "gazette",
      "title": "국가기술표준원고시제2024-0445호(한국산업표준 개정 예고)",
      "institution": "산업통상자원부",
      "date": "2024-10-21",
      "docType": "고시",
      "excerpt": "",
      "detailPath": "docs/details/gazette/gazette-2024-10-21-045_산업통상자원부_국가기술표준원고시제2024_0445호_한국산업표준_개정_예고-a521a0549d.json"
    },
    {
      "id": "gazette-2024-10-21-046_산업통상자원부_국가기술표준원고시제2024_0442호_한국산업표준_확인_고시-d250a2f350",
      "layer": "gazette",
      "title": "국가기술표준원고시제2024-0442호(한국산업표준 확인 고시)",
      "institution": "산업통상자원부",
      "date": "2024-10-21",
      "docType": "고시",
      "excerpt": "",
      "detailPath": "docs/details/gazette/gazette-2024-10-21-046_산업통상자원부_국가기술표준원고시제2024_0442호_한국산업표준_확인_고시-d250a2f350.json"
    },
    {
      "id": "gazette-2024-10-21-047_산업통상자원부_국가기술표준원고시제2024_0447호_한국산업표준_개정-99e193233d",
      "layer": "gazette",
      "title": "국가기술표준원고시제2024-0447호(한국산업표준 개정)",
      "institution": "산업통상자원부",
      "date": "2024-10-21",
      "docType": "고시",
      "excerpt": "",
      "detailPath": "docs/details/gazette/gazette-2024-10-21-047_산업통상자원부_국가기술표준원고시제2024_0447호_한국산업표준_개정-99e193233d.json"
    },
    {
      "id": "gazette-2024-10-21-048_산업통상자원부_국가기술표준원고시제2024_0428호_한국산업표준_개정_고시-33196635b5",
      "layer": "gazette",
      "title": "국가기술표준원고시제2024-0428호(한국산업표준 개정  고시)",
      "institution": "산업통상자원부",
      "date": "2024-10-21",
      "docType": "고시",
      "excerpt": "",
      "detailPath": "docs/details/gazette/gazette-2024-10-21-048_산업통상자원부_국가기술표준원고시제2024_0428호_한국산업표준_개정_고시-33196635b5.json"
    },
    {
      "id": "gazette-2024-10-21-049_새만금개발청_새만금개발청공고제2024_65호_공유수면_점용_사용_허가신청에_따른_이해관계자의_의견수렴_공고-22eafd3547",
      "layer": "gazette",
      "title": "새만금개발청공고제2024-65호(공유수면 점용ㆍ사용 허가신청에 따른 이해관계자의 의견수렴 공고)",
      "institution": "새만금개발청",
      "date": "2024-10-21",
      "docType": "공고",
      "excerpt": "",
      "detailPath": "docs/details/gazette/gazette-2024-10-21-049_새만금개발청_새만금개발청공고제2024_65호_공유수면_점용_사용_허가신청에_따른_이해관계자의_의견수렴_공고-22eafd3547.json"
    },
    {
      "id": "gazette-2024-10-21-050_식품의약품안전처_서울지방식품의약품안전청공고제2024_147호_행정처분_사전_청문_통지_공고_2024_147호-3e35f3354a",
      "layer": "gazette",
      "title": "서울지방식품의약품안전청공고제2024-147호(행정처분 사전(청문)통지 공고(2024-147호))",
      "institution": "식품의약품안전처",
      "date": "2024-10-21",
      "docType": "공고",
      "excerpt": "",
      "detailPath": "docs/details/gazette/gazette-2024-10-21-050_식품의약품안전처_서울지방식품의약품안전청공고제2024_147호_행정처분_사전_청문_통지_공고_2024_147호-3e35f3354a.json"
    },
    {
      "id": "gazette-2024-10-21-051_인천광역시_인천광역시고시제2024_302호_도시관리계획_용도구역_개발제한구역_결정_변경_및_지형도면_고시-42e988a73f",
      "layer": "gazette",
      "title": "인천광역시고시제2024-302호(도시관리계획(용도구역: 개발제한구역) 결정(변경) 및 지형도면 고시)",
      "institution": "인천광역시",
      "date": "2024-10-21",
      "docType": "지방자치단체",
      "excerpt": "",
      "detailPath": "docs/details/gazette/gazette-2024-10-21-051_인천광역시_인천광역시고시제2024_302호_도시관리계획_용도구역_개발제한구역_결정_변경_및_지형도면_고시-42e988a73f.json"
    },
    {
      "id": "gazette-2024-10-21-052_조달청_조달청공고제2024_356호_부정당업자_입찰참가자격_제한_처분을_위한_공시송달-58c3960bc7",
      "layer": "gazette",
      "title": "조달청공고제2024-356호(부정당업자 입찰참가자격 제한 처분을 위한 공시송달)",
      "institution": "조달청",
      "date": "2024-10-21",
      "docType": "공고",
      "excerpt": "",
      "detailPath": "docs/details/gazette/gazette-2024-10-21-052_조달청_조달청공고제2024_356호_부정당업자_입찰참가자격_제한_처분을_위한_공시송달-58c3960bc7.json"
    },
    {
      "id": "gazette-2024-10-21-053_중소벤처기업부_중소벤처기업부고시제2024_79호_지역특화발전특구_계획변경_고시-070e07bbb1",
      "layer": "gazette",
      "title": "중소벤처기업부고시제2024-79호(지역특화발전특구 계획변경 고시)",
      "institution": "중소벤처기업부",
      "date": "2024-10-21",
      "docType": "고시",
      "excerpt": "",
      "detailPath": "docs/details/gazette/gazette-2024-10-21-053_중소벤처기업부_중소벤처기업부고시제2024_79호_지역특화발전특구_계획변경_고시-070e07bbb1.json"
    },
    {
      "id": "gazette-2024-10-21-054_해양경찰청_부산해양경찰서고시제2024_03호_부산해양경찰서_수상레저활동_금지구역_지정_고시-d852319984",
      "layer": "gazette",
      "title": "부산해양경찰서고시제2024-03호(「(부산해양경찰서) 수상레저활동 금지구역 지정 고시」)",
      "institution": "해양경찰청",
      "date": "2024-10-21",
      "docType": "고시",
      "excerpt": "",
      "detailPath": "docs/details/gazette/gazette-2024-10-21-054_해양경찰청_부산해양경찰서고시제2024_03호_부산해양경찰서_수상레저활동_금지구역_지정_고시-d852319984.json"
    },
    {
      "id": "gazette-2024-10-21-055_해양경찰청_해양수산부령제696호_해양경찰청_소속_경찰공무원_복제에_관한_규칙_일부개정령-71778dba77",
      "layer": "gazette",
      "title": "해양수산부령제696호(해양경찰청 소속 경찰공무원 복제에 관한 규칙 일부개정령)",
      "institution": "해양경찰청",
      "date": "2024-10-21",
      "docType": "부령",
      "excerpt": "",
      "detailPath": "docs/details/gazette/gazette-2024-10-21-055_해양경찰청_해양수산부령제696호_해양경찰청_소속_경찰공무원_복제에_관한_규칙_일부개정령-71778dba77.json"
    },
    {
      "id": "gazette-2024-10-21-056_해양수산부_마산지방해양수산청고시제2024_81호_사설항로표지_폐지_고시_통영항동우A호등부표_외_1기-cc04c33239",
      "layer": "gazette",
      "title": "마산지방해양수산청고시제2024-81호(사설항로표지 폐지 고시(통영항동우A호등부표 외 1기))",
      "institution": "해양수산부",
      "date": "2024-10-21",
      "docType": "고시",
      "excerpt": "",
      "detailPath": "docs/details/gazette/gazette-2024-10-21-056_해양수산부_마산지방해양수산청고시제2024_81호_사설항로표지_폐지_고시_통영항동우A호등부표_외_1기-cc04c33239.json"
    },
    {
      "id": "gazette-2024-10-21-057_해양수산부_여수지방해양수산청고시제2024_97호_항로표지_신설_서상등표-2f471aacba",
      "layer": "gazette",
      "title": "여수지방해양수산청고시제2024-97호(항로표지 신설(서상등표))",
      "institution": "해양수산부",
      "date": "2024-10-21",
      "docType": "고시",
      "excerpt": "",
      "detailPath": "docs/details/gazette/gazette-2024-10-21-057_해양수산부_여수지방해양수산청고시제2024_97호_항로표지_신설_서상등표-2f471aacba.json"
    },
    {
      "id": "gazette-2024-10-21-058_해양수산부_평택지방해양수산청공고제2024_127호_비관리청_항만개발사업_준공_공고_평택당진항_동부두_7번선석_전기_충전소_-52d4e56ce9",
      "layer": "gazette",
      "title": "평택지방해양수산청공고제2024-127호( 비관리청 항만개발사업 준공 공고[평택당진항 동부두 7번선석 전기 충전소 설치공사])",
      "institution": "해양수산부",
      "date": "2024-10-21",
      "docType": "공고",
      "excerpt": "",
      "detailPath": "docs/details/gazette/gazette-2024-10-21-058_해양수산부_평택지방해양수산청공고제2024_127호_비관리청_항만개발사업_준공_공고_평택당진항_동부두_7번선석_전기_충전소_-52d4e56ce9.json"
    },
    {
      "id": "gazette-2024-10-21-059_해양수산부_평택지방해양수산청공고제2024_119호_항만개발사업_준공_공고_비관리청_항만개발사업_한국석유공사_제1부두_박지_-86b9c4bb16",
      "layer": "gazette",
      "title": "평택지방해양수산청공고제2024-119호(항만개발사업 준공 공고[비관리청 항만개발사업 한국석유공사 제1부두 박지 유지준설])",
      "institution": "해양수산부",
      "date": "2024-10-21",
      "docType": "공고",
      "excerpt": "",
      "detailPath": "docs/details/gazette/gazette-2024-10-21-059_해양수산부_평택지방해양수산청공고제2024_119호_항만개발사업_준공_공고_비관리청_항만개발사업_한국석유공사_제1부두_박지_-86b9c4bb16.json"
    },
    {
      "id": "gazette-2024-10-21-060_해양수산부_평택지방해양수산청공고제2024_134호_비관리청_항만개발사업_준공_공고_한일시멘트_주_서부두_1번선석_버너_건조-28a72fe44a",
      "layer": "gazette",
      "title": "평택지방해양수산청공고제2024-134호(비관리청 항만개발사업 준공 공고[(한일시멘트(주))서부두 1번선석 버너(건조기)개선공사])",
      "institution": "해양수산부",
      "date": "2024-10-21",
      "docType": "공고",
      "excerpt": "",
      "detailPath": "docs/details/gazette/gazette-2024-10-21-060_해양수산부_평택지방해양수산청공고제2024_134호_비관리청_항만개발사업_준공_공고_한일시멘트_주_서부두_1번선석_버너_건조-28a72fe44a.json"
    },
    {
      "id": "gazette-2024-10-21-061_해양수산부_평택지방해양수산청공고제2024_135호_비관리청_항만개발사업_준공_공고_한일시멘트_주_서부두_3번선석_버너_건조-6af89de8ae",
      "layer": "gazette",
      "title": "평택지방해양수산청공고제2024-135호(비관리청 항만개발사업 준공 공고[(한일시멘트(주))서부두 3번선석 버너(건조기)개선공사])",
      "institution": "해양수산부",
      "date": "2024-10-21",
      "docType": "공고",
      "excerpt": "",
      "detailPath": "docs/details/gazette/gazette-2024-10-21-061_해양수산부_평택지방해양수산청공고제2024_135호_비관리청_항만개발사업_준공_공고_한일시멘트_주_서부두_3번선석_버너_건조-6af89de8ae.json"
    },
    {
      "id": "gazette-2024-10-21-062_행정안전부_대통령훈령제472호_중앙재난안전대책본부_구성_및_운영_등에_관한_규정_일부개정령-5eda62173c",
      "layer": "gazette",
      "title": "대통령훈령제472호(중앙재난안전대책본부 구성 및 운영 등에 관한 규정 일부개정령)",
      "institution": "행정안전부",
      "date": "2024-10-21",
      "docType": "훈령",
      "excerpt": "",
      "detailPath": "docs/details/gazette/gazette-2024-10-21-062_행정안전부_대통령훈령제472호_중앙재난안전대책본부_구성_및_운영_등에_관한_규정_일부개정령-5eda62173c.json"
    },
    {
      "id": "gazette-2024-10-21-063_행정안전부_행정안전부공고제2024_1436호_울릉도_흑산도_등_국토외곽_먼섬_지원_특별법_시행령_제정령_안_입법예고-b740361e61",
      "layer": "gazette",
      "title": "행정안전부공고제2024-1436호(「울릉도·흑산도 등 국토외곽 먼섬 지원 특별법 시행령」 제정령(안) 입법예고)",
      "institution": "행정안전부",
      "date": "2024-10-21",
      "docType": "공고",
      "excerpt": "",
      "detailPath": "docs/details/gazette/gazette-2024-10-21-063_행정안전부_행정안전부공고제2024_1436호_울릉도_흑산도_등_국토외곽_먼섬_지원_특별법_시행령_제정령_안_입법예고-b740361e61.json"
    },
    {
      "id": "gazette-2024-10-21-064_환경부_환경부고시제2024_194호_소백산국립공원_초암사_공중화장실_신축_공원사업시행계획_결정-edb7700f48",
      "layer": "gazette",
      "title": "환경부고시제2024-194호(소백산국립공원 초암사 공중화장실 신축 공원사업시행계획 결정)",
      "institution": "환경부",
      "date": "2024-10-21",
      "docType": "고시",
      "excerpt": "",
      "detailPath": "docs/details/gazette/gazette-2024-10-21-064_환경부_환경부고시제2024_194호_소백산국립공원_초암사_공중화장실_신축_공원사업시행계획_결정-edb7700f48.json"
    },
    {
      "id": "gazette-2024-10-21-065_환경부_환경부고시제2024_205호_지리산국립공원_노고단대피소_부대시설_정비_용소_공중화장실_및_화엄사_전망대_신축_공원사-505419196c",
      "layer": "gazette",
      "title": "환경부고시제2024-205호(지리산국립공원 노고단대피소 부대시설 정비, 용소 공중화장실 및 화엄사 전망대 신축 공원사업시행계획 결정)",
      "institution": "환경부",
      "date": "2024-10-21",
      "docType": "고시",
      "excerpt": "",
      "detailPath": "docs/details/gazette/gazette-2024-10-21-065_환경부_환경부고시제2024_205호_지리산국립공원_노고단대피소_부대시설_정비_용소_공중화장실_및_화엄사_전망대_신축_공원사-505419196c.json"
    },
    {
      "id": "gazette-2024-10-21-066_환경부_영산강유역환경청고시제2024_44호_하천공사_시행계획_고시_황룡강_송정2지구_하천환경정비사업-419e9be5cc",
      "layer": "gazette",
      "title": "영산강유역환경청고시제2024-44호(하천공사 시행계획 고시(황룡강 송정2지구 하천환경정비사업))",
      "institution": "환경부",
      "date": "2024-10-21",
      "docType": "고시",
      "excerpt": "",
      "detailPath": "docs/details/gazette/gazette-2024-10-21-066_환경부_영산강유역환경청고시제2024_44호_하천공사_시행계획_고시_황룡강_송정2지구_하천환경정비사업-419e9be5cc.json"
    },
    {
      "id": "gazette-2024-10-21-067_환경부_한강홍수통제소고시제2024_96호_하천수_사용허가_고시-b2cfa8655a",
      "layer": "gazette",
      "title": "한강홍수통제소고시제2024-96호(하천수 사용허가 고시)",
      "institution": "환경부",
      "date": "2024-10-21",
      "docType": "고시",
      "excerpt": "",
      "detailPath": "docs/details/gazette/gazette-2024-10-21-067_환경부_한강홍수통제소고시제2024_96호_하천수_사용허가_고시-b2cfa8655a.json"
    }
  ]
}