{
  "id": "gazette-2026-04-06-037_기후에너지환경부_기후에너지환경부공고제2026_359호_국내_폐기물_재활용_촉진을_위해_수입이_제한되는_폐기물_품목_고시_일부개정안_행정예고",
  "detailPath": "docs/details/gazette/gazette-2026-04-06-037_기후에너지환경부_기후에너지환경부공고제2026_359호_국내_폐기물_재활용_촉진을_위해_수입이_제한되는_폐기물_품목_고시_일부개정안_행정예고.json",
  "layer": "gazette",
  "file": "037_기후에너지환경부_기후에너지환경부공고제2026_359호_국내_폐기물_재활용_촉진을_위해_수입이_제한되는_폐기물_품목_고시_일부개정안_행정예고.md",
  "title": "기후에너지환경부공고제2026-359호(「국내 폐기물 재활용 촉진을 위해 수입이 제한되는 폐기물 품목 고시」 일부개정안 행정예고)",
  "institution": "기후에너지환경부",
  "publisher": "기후에너지환경부",
  "date": "2026-04-06",
  "docType": "공고",
  "formType": "공고",
  "basisLaw": "행정절차법 제46조",
  "pdfUrl": "https://gwanbo.go.kr/ezpdf/customLayout.jsp?contentId=I0000000000000001775107028041000&tocId=I0000000000000001774960138445000&isTocOrder=N&name=%EA%B8%B0%ED%9B%84%EC%97%90%EB%84%88%EC%A7%80%ED%99%98%EA%B2%BD%EB%B6%80%EA%B3%B5%EA%B3%A0%EC%A0%9C2026-359%ED%98%B8%28%E3%80%8C%EA%B5%AD%EB%82%B4+%ED%8F%90%EA%B8%B0%EB%AC%BC+%EC%9E%AC%ED%99%9C%EC%9A%A9+%EC%B4%89%EC%A7%84%EC%9D%84+%EC%9C%84%ED%95%B4+%EC%88%98%EC%9E%85%EC%9D%B4+%EC%A0%9C%ED%95%9C%EB%90%98%EB%8A%94+%ED%8F%90%EA%B8%B0%EB%AC%BC+%ED%92%88%EB%AA%A9+%EA%B3%A0%EC%8B%9C%E3%80%8D+%EC%9D%BC%EB%B6%80%EA%B0%9C%EC%A0%95%EC%95%88+%ED%96%89%EC%A0%95%EC%98%88%EA%B3%A0%29",
  "hasRaw": true,
  "hasReadable": true,
  "excerpt": "◉기후에너지환경부공고 제2026-359호 「국내 폐기물 재활용 촉진을 위해 수입이 제한되는 폐기물 품목 고시」를 일부개정하는 데에 있 어, 그 개정이유와 주요내용을 국민에게 미리 알려 이에 대한 의견을 듣기 위하여 「행정절차법」 제 46조에 따라 다음과 같이 공고합니다. 2026년 04월 06일 기후에너지환경부장관",
  "metaPath": "data/2026/2026-04/2026-04-06/037_기후에너지환경부_기후에너지환경부공고제2026_359호_국내_폐기물_재활용_촉진을_위해_수입이_제한되는_폐기물_품목_고시_일부개정안_행정예고.md",
  "rawPath": "opendataloader-output/2026-04-06/037_기후에너지환경부_기후에너지환경부공고제2026_359호_국내_폐기물_재활용_촉진을_위해_수입이_제한되는_폐기물_품목_고시_일부개정안_행정예고.md",
  "readablePath": "readable-final/2026-04-06/037_기후에너지환경부_기후에너지환경부공고제2026_359호_국내_폐기물_재활용_촉진을_위해_수입이_제한되는_폐기물_품목_고시_일부개정안_행정예고.md"
}