{
  "id": "gazette-2025-07-08-071_충청남도_천안시공고제2025_1671호_빙그레_일반산업단지_준공인가_공고",
  "detailPath": "docs/details/gazette/gazette-2025-07-08-071_충청남도_천안시공고제2025_1671호_빙그레_일반산업단지_준공인가_공고.json",
  "layer": "gazette",
  "file": "071_충청남도_천안시공고제2025_1671호_빙그레_일반산업단지_준공인가_공고.md",
  "title": "천안시공고제2025-1671호(빙그레 일반산업단지 준공인가 공고)",
  "institution": "충청남도",
  "publisher": "충청남도",
  "date": "2025-07-08",
  "docType": "지방자치단체",
  "formType": "지방자치단체",
  "basisLaw": "산업입지 및 개발에 관한 법률 시행규칙 제12조",
  "pdfUrl": "https://gwanbo.go.kr/ezpdf/customLayout.jsp?contentId=I0000000000000001751613072893000&tocId=I0000000000000001751414854118000&isTocOrder=N&name=%EC%B2%9C%EC%95%88%EC%8B%9C%EA%B3%B5%EA%B3%A0%EC%A0%9C2025-1671%ED%98%B8%28%EB%B9%99%EA%B7%B8%EB%A0%88+%EC%9D%BC%EB%B0%98%EC%82%B0%EC%97%85%EB%8B%A8%EC%A7%80+%EC%A4%80%EA%B3%B5%EC%9D%B8%EA%B0%80+%EA%B3%B5%EA%B3%A0%29",
  "hasRaw": false,
  "hasReadable": false,
  "excerpt": "",
  "metaPath": "data/2025/2025-07/2025-07-08/071_충청남도_천안시공고제2025_1671호_빙그레_일반산업단지_준공인가_공고.md",
  "rawPath": "",
  "readablePath": ""
}