{
  "id": "gazette-2026-04-02-058_조달청_조달청공고제2026_146호_부정당업자_제재_처분_예정_사전통지_및_의견제출_요청-604b0f8193",
  "detailPath": "docs/details/gazette/gazette-2026-04-02-058_조달청_조달청공고제2026_146호_부정당업자_제재_처분_예정_사전통지_및_의견제출_요청-604b0f8193.json",
  "layer": "gazette",
  "file": "058_조달청_조달청공고제2026_146호_부정당업자_제재_처분_예정_사전통지_및_의견제출_요청.md",
  "title": "조달청공고제2026-146호(부정당업자 제재 처분(예정) 사전통지 및 의견제출 요청)",
  "institution": "조달청",
  "publisher": "조달청",
  "date": "2026-04-02",
  "docType": "공고",
  "formType": "공고",
  "basisLaw": "행정절차법 제14조",
  "pdfUrl": "https://gwanbo.go.kr/ezpdf/customLayout.jsp?contentId=I0000000000000001774941717837000&tocId=I0000000000000001774584064851000&isTocOrder=N&name=%EC%A1%B0%EB%8B%AC%EC%B2%AD%EA%B3%B5%EA%B3%A0%EC%A0%9C2026-146%ED%98%B8%28%EB%B6%80%EC%A0%95%EB%8B%B9%EC%97%85%EC%9E%90+%EC%A0%9C%EC%9E%AC+%EC%B2%98%EB%B6%84%28%EC%98%88%EC%A0%95%29+%EC%82%AC%EC%A0%84%ED%86%B5%EC%A7%80+%EB%B0%8F+%EC%9D%98%EA%B2%AC%EC%A0%9C%EC%B6%9C+%EC%9A%94%EC%B2%AD%29",
  "hasRaw": true,
  "hasReadable": true,
  "excerpt": "◉조달청공고 제2026-146호 부정당업자 입찰참가자격 제한 처분을 위한 사전통지 공시송달 다음 당사자는「국가를 당사자로 하는 계약에 관한 법률」제27조 제1항 제1호 나목 및 같은법 시 행규칙 제76조 별표2 개별기준 제3호 나목에 의한 부정당업자 입찰참가자격제한 처분의 예정자로서 ‘부정당업자 입찰참가자격제한 처분 사전통지 및 의견제출 안내’ 문서를 우편 송달하였으나 수취 인 폐문부재로 반",
  "metaPath": "data/2026/2026-04/2026-04-02/058_조달청_조달청공고제2026_146호_부정당업자_제재_처분_예정_사전통지_및_의견제출_요청.md",
  "rawPath": "opendataloader-output/2026-04-02/058_조달청_조달청공고제2026_146호_부정당업자_제재_처분_예정_사전통지_및_의견제출_요청.md",
  "readablePath": "readable-final/2026-04-02/058_조달청_조달청공고제2026_146호_부정당업자_제재_처분_예정_사전통지_및_의견제출_요청.md"
}