{
  "id": "gazette-2025-01-08-024_기획재정부_기획재정부공고제2025_2호_국고채전문딜러에_대한_금융지원에_관한_기준_일부개정고시안에_대한_행정예고-42c47a465f",
  "detailPath": "docs/details/gazette/gazette-2025-01-08-024_기획재정부_기획재정부공고제2025_2호_국고채전문딜러에_대한_금융지원에_관한_기준_일부개정고시안에_대한_행정예고-42c47a465f.json",
  "layer": "gazette",
  "file": "024_기획재정부_기획재정부공고제2025_2호_국고채전문딜러에_대한_금융지원에_관한_기준_일부개정고시안에_대한_행정예고.md",
  "title": "기획재정부공고제2025-2호(국고채전문딜러에 대한 금융지원에 관한 기준 일부개정고시안에 대한 행정예고)",
  "institution": "기획재정부",
  "publisher": "기획재정부",
  "date": "2025-01-08",
  "docType": "공고",
  "formType": "공고",
  "basisLaw": "행정절차법 제46조",
  "pdfUrl": "https://gwanbo.go.kr/ezpdf/customLayout.jsp?contentId=I0000000000000001736148095942000&tocId=I0000000000000001735868900136000&isTocOrder=N&name=%EA%B8%B0%ED%9A%8D%EC%9E%AC%EC%A0%95%EB%B6%80%EA%B3%B5%EA%B3%A0%EC%A0%9C2025-2%ED%98%B8%28%EA%B8%B0%ED%9A%8D%EC%9E%AC%EC%A0%95%EB%B6%80%EA%B3%B5%EA%B3%A0%29",
  "hasRaw": false,
  "hasReadable": false,
  "excerpt": "",
  "metaPath": "data/2025/2025-01/2025-01-08/024_기획재정부_기획재정부공고제2025_2호_국고채전문딜러에_대한_금융지원에_관한_기준_일부개정고시안에_대한_행정예고.md",
  "rawPath": "",
  "readablePath": ""
}